ASM_Charts/asm.sv
module asm (
    input  logic       clk,
    input  logic       rst,
    input  logic       in,
    output logic [1:0] y,
    output logic       z
);
  parameter S0 = 2'b00;
  parameter S1 = 2'b01;
  parameter S2 = 2'b10;
  parameter S3 = 2'b11;

  logic [1:0] state, next_state;

  always_ff @(posedge clk or posedge rst) begin : state_trans
    if (rst) begin
      state <= S0;
      y <= '0;
      z <= '0;
    end else begin
      state <= next_state;
    end
  end

  always_comb begin : state_trans_logic
    case (state)
      S0: next_state = in ? S1 : S0;
      S1: next_state = in ? S1 : S2;
      S2: next_state = in ? S1 : S3;
      S3: next_state = S0;
      default: next_state = S0;
    endcase
  end

  // Output logic
  always_comb begin
    y = (state == S1);
    y = (state == S2 || state == S3);
    z = ((state == S1 && in) || (state == S2 && in));
  end

endmodule

ASM_Charts/asm_tb.sv
module asm_tb;
  logic       clk;
  logic       rst;
  logic       in;
  logic [1:0] y;
  logic       z;

  asm uut (
      .clk(clk),
      .rst(rst),
      .in (in),
      .y  (y),
      .z  (z)
  );

  initial begin
    $dumpfile("asm.vcd");
    $dumpvars(0, asm_tb);
  end

  always #5 clk = ~clk;

  initial begin
    clk = 0;
    rst = 1;
    in  = 0;
    #10;
    rst = 0;
    in  = 0;
    #10;
    in = 1;
    #10;
    in = 1;
    #10;
    in = 0;
    #10;
    in = 1;
    #10;
    in = 0;
    #10;
    in = 0;
    #10;
    in = 1;
    $finish;
  end
endmodule

ASM_Charts/asm.vcd
$date
	Sat Jun 28 20:42:06 2025
$end
$version
	Icarus Verilog
$end
$timescale
	1s
$end
$scope module asm_tb $end
$var wire 1 ! z $end
$var wire 2 " y [1:0] $end
$var reg 1 # clk $end
$var reg 1 $ in $end
$var reg 1 % rst $end
$scope module uut $end
$var wire 1 # clk $end
$var wire 1 $ in $end
$var wire 1 % rst $end
$var parameter 2 & S0 $end
$var parameter 2 ' S1 $end
$var parameter 2 ( S2 $end
$var parameter 2 ) S3 $end
$var reg 2 * next_state [1:0] $end
$var reg 2 + state [1:0] $end
$var reg 2 , y [1:0] $end
$var reg 1 ! z $end
$scope begin state_trans $end
$upscope $end
$scope begin state_trans_logic $end
$upscope $end
$upscope $end
$upscope $end
$enddefinitions $end
$comment Show the parameter values. $end
$dumpall
b11 )
b10 (
b1 '
b0 &
$end
#0
$dumpvars
b0 ,
b0 +
b0 *
1%
0$
0#
b0 "
0!
$end
#5
1#
#10
0#
0%
#15
1#
#20
b1 *
0#
1$
#25
1!
b0 "
b0 ,
b1 +
1#
#30
0#
#35
1#
#40
b10 *
0!
b0 "
b0 ,
0#
0$
#45
b11 *
b1 "
b1 ,
b10 +
1#
#50
b1 *
1!
b1 "
b1 ,
0#
1$
#55
b0 "
b0 ,
b1 +
1#
#60
b10 *
0!
b0 "
b0 ,
0#
0$
#65
b11 *
b1 "
b1 ,
b10 +
1#
#70
0#
#75
b0 *
b1 "
b1 ,
b11 +
1#
#80
b1 "
b1 ,
0#
1$
