8_bit_CSA/muxb.sv
// NOTE: 2-to-1 MUX with 4 bit inputs and 4 bit output and 1 bit select
module muxb (
    input  logic [3:0] d0,
    input  logic [3:0] d1,
    input  logic       s,
    output logic [3:0] y
);

  assign y = s ? d1 : d0;

endmodule

8_bit_CSA/mux2.sv
module mux2 (
    input  logic [1:0] d,
    input  logic       s,
    output logic       y
);

  assign y = s ? d[1] : d[0];

  // always_comb begin : mux
  //   if (s) begin
  //     y = d[1];
  //   end else begin
  //     y = d[0];
  //   end
  // end
endmodule

3x3_Mult/half_adder.sv
module half_adder (
    input  logic a,
    input  logic b,
    output logic sum,
    output logic cout
);
  assign {cout, sum} = a + b;
endmodule

full_adder.sv
module full_adder (
    input  logic a,
    input  logic b,
    input  logic cin,
    output logic cout,
    output logic sum
);
  logic ha1_sum, ha1_cout, ha2_cout;

  half_adder ha1 (
      .a(a),
      .b(b),
      .sum(ha1_sum),
      .cout(ha1_cout)
  );
  half_adder ha2 (
      .a(cin),
      .b(ha1_sum),
      .sum(sum),
      .cout(ha2_cout)
  );

  assign cout = ha2_cout | ha1_cout;
endmodule

8_bit_CSA/rca4.sv
`include "../3x3_Mult/half_adder.sv"
`include "../3x3_Mult/full_adder.sv"

module rca4 (
    input  logic [3:0] a,
    input  logic [3:0] b,
    input  logic       cin,
    output logic       cout,
    output logic [3:0] sum
);

  logic fa1_out, fa2_out, fa3_out;

  full_adder fa1 (
      .a(a[0]),
      .b(b[0]),
      .cin(cin),
      .cout(fa1_out),
      .sum(sum[0])
  );
  full_adder fa2 (
      .a(a[1]),
      .b(b[1]),
      .cin(fa1_out),
      .cout(fa2_out),
      .sum(sum[1])
  );
  full_adder fa3 (
      .a(a[2]),
      .b(b[2]),
      .cin(fa2_out),
      .cout(fa3_out),
      .sum(sum[2])
  );
  full_adder fa4 (
      .a(a[3]),
      .b(b[3]),
      .cin(fa3_out),
      .cout(cout),
      .sum(sum[3])
  );
endmodule

8_bit_CSA/csa8.sv
`include "../8_bit_CSA/mux2.sv"
`include "../8_bit_CSA/muxb.sv"
`include "../8_bit_CSA/rca4.sv"

module csa8 (
    input  logic [7:0] a,
    input  logic [7:0] b,
    input  logic       cin,
    output logic       cout,
    output logic [7:0] sum
);

  // Internal Registers
  logic a1_cout, cout_mux_d0, cout_mux_d1;
  logic [3:0] sa;
  logic [3:0] sb;


  // Ripple carry adder for lower 4 sum bits
  rca4 a1 (
      .a(a[3:0]),
      .b(b[3:0]),
      .cin(cin),
      .cout(a1_cout),
      .sum(sum[3:0])
  );

  // Ripple carry adder for higher 4 bits when cin is 0
  rca4 a2 (
      .a(a[7:4]),
      .b(b[7:4]),
      .cin(1'b0),
      .cout(cout_mux_d0),
      .sum(sa)
  );

  // Ripple carry adder for higher 4 bits when cin is 1
  rca4 a3 (
      .a(a[7:4]),
      .b(b[7:4]),
      .cin(1'b1),
      .cout(cout_mux_d1),
      .sum(sb)
  );

  // 2-1 Mux to handle cout
  mux2 cout_mux (
      .d({cout_mux_d1, cout_mux_d0}),
      .s(a1_cout),
      .y(cout)
  );

  // 2-1 4 bit i/o mux to handle upper 4 sum bits
  muxb sum_hi_4 (
      .d0(sa),
      .d1(sb),
      .s (a1_cout),
      .y (sum[7:4])
  );
endmodule

8_bit_CSA/csa8_tb.sv
module csa8_tb;
  logic [7:0] a;
  logic [7:0] b;
  logic       cin;
  logic       cout;
  logic [7:0] sum;

  csa8 uut (
      .a(a),
      .b(b),
      .cin(cin),
      .cout(cout),
      .sum(sum)
  );

  // VCD dump
  initial begin
    $dumpfile("csa8.vcd");
    $dumpvars(0, csa8_tb);
  end


  initial begin
    $display("    a    b    cin |    sum    cout");
    $display("-----------------------------------");
    for (int i = 0; i < 500; i++) begin
      a   = $urandom;
      b   = $urandom;
      cin = $urandom_range(0, 1);
      #10;
      $display("    %0d    %0d    %0d |    %0d    %0d", a, b, cin, cout, sum);

      // TODO: Functional Coverage
      // ......
      //
    end
    $display("Random Test Complete");
    $finish;
  end
endmodule

8_bit_CSA/csa8.vcd
$date
	Wed Jun  4 17:10:02 2025
$end
$version
	Icarus Verilog
$end
$timescale
	1s
$end
$scope module csa8_tb $end
$var wire 8 ! sum [7:0] $end
$var wire 1 " cout $end
$var reg 8 # a [7:0] $end
$var reg 8 $ b [7:0] $end
$var reg 1 % cin $end
$scope module uut $end
$var wire 8 & a [7:0] $end
$var wire 8 ' b [7:0] $end
$var wire 1 % cin $end
$var wire 8 ( sum [7:0] $end
$var wire 4 ) sb [3:0] $end
$var wire 4 * sa [3:0] $end
$var wire 1 + cout_mux_d1 $end
$var wire 1 , cout_mux_d0 $end
$var wire 1 " cout $end
$var wire 1 - a1_cout $end
$scope module a1 $end
$var wire 4 . a [3:0] $end
$var wire 4 / b [3:0] $end
$var wire 1 % cin $end
$var wire 4 0 sum [3:0] $end
$var wire 1 1 fa3_out $end
$var wire 1 2 fa2_out $end
$var wire 1 3 fa1_out $end
$var wire 1 - cout $end
$scope module fa1 $end
$var wire 1 4 a $end
$var wire 1 5 b $end
$var wire 1 % cin $end
$var wire 1 3 cout $end
$var wire 1 6 sum $end
$var wire 1 7 ha2_cout $end
$var wire 1 8 ha1_sum $end
$var wire 1 9 ha1_cout $end
$scope module ha1 $end
$var wire 1 4 a $end
$var wire 1 5 b $end
$var wire 1 8 sum $end
$var wire 1 9 cout $end
$upscope $end
$scope module ha2 $end
$var wire 1 % a $end
$var wire 1 8 b $end
$var wire 1 6 sum $end
$var wire 1 7 cout $end
$upscope $end
$upscope $end
$scope module fa2 $end
$var wire 1 : a $end
$var wire 1 ; b $end
$var wire 1 3 cin $end
$var wire 1 2 cout $end
$var wire 1 < sum $end
$var wire 1 = ha2_cout $end
$var wire 1 > ha1_sum $end
$var wire 1 ? ha1_cout $end
$scope module ha1 $end
$var wire 1 : a $end
$var wire 1 ; b $end
$var wire 1 > sum $end
$var wire 1 ? cout $end
$upscope $end
$scope module ha2 $end
$var wire 1 3 a $end
$var wire 1 > b $end
$var wire 1 < sum $end
$var wire 1 = cout $end
$upscope $end
$upscope $end
$scope module fa3 $end
$var wire 1 @ a $end
$var wire 1 A b $end
$var wire 1 2 cin $end
$var wire 1 1 cout $end
$var wire 1 B sum $end
$var wire 1 C ha2_cout $end
$var wire 1 D ha1_sum $end
$var wire 1 E ha1_cout $end
$scope module ha1 $end
$var wire 1 @ a $end
$var wire 1 A b $end
$var wire 1 D sum $end
$var wire 1 E cout $end
$upscope $end
$scope module ha2 $end
$var wire 1 2 a $end
$var wire 1 D b $end
$var wire 1 B sum $end
$var wire 1 C cout $end
$upscope $end
$upscope $end
$scope module fa4 $end
$var wire 1 F a $end
$var wire 1 G b $end
$var wire 1 1 cin $end
$var wire 1 - cout $end
$var wire 1 H sum $end
$var wire 1 I ha2_cout $end
$var wire 1 J ha1_sum $end
$var wire 1 K ha1_cout $end
$scope module ha1 $end
$var wire 1 F a $end
$var wire 1 G b $end
$var wire 1 J sum $end
$var wire 1 K cout $end
$upscope $end
$scope module ha2 $end
$var wire 1 1 a $end
$var wire 1 J b $end
$var wire 1 H sum $end
$var wire 1 I cout $end
$upscope $end
$upscope $end
$upscope $end
$scope module a2 $end
$var wire 4 L a [3:0] $end
$var wire 4 M b [3:0] $end
$var wire 1 N cin $end
$var wire 4 O sum [3:0] $end
$var wire 1 P fa3_out $end
$var wire 1 Q fa2_out $end
$var wire 1 R fa1_out $end
$var wire 1 , cout $end
$scope module fa1 $end
$var wire 1 S a $end
$var wire 1 T b $end
$var wire 1 N cin $end
$var wire 1 R cout $end
$var wire 1 U sum $end
$var wire 1 V ha2_cout $end
$var wire 1 W ha1_sum $end
$var wire 1 X ha1_cout $end
$scope module ha1 $end
$var wire 1 S a $end
$var wire 1 T b $end
$var wire 1 W sum $end
$var wire 1 X cout $end
$upscope $end
$scope module ha2 $end
$var wire 1 N a $end
$var wire 1 W b $end
$var wire 1 U sum $end
$var wire 1 V cout $end
$upscope $end
$upscope $end
$scope module fa2 $end
$var wire 1 Y a $end
$var wire 1 Z b $end
$var wire 1 R cin $end
$var wire 1 Q cout $end
$var wire 1 [ sum $end
$var wire 1 \ ha2_cout $end
$var wire 1 ] ha1_sum $end
$var wire 1 ^ ha1_cout $end
$scope module ha1 $end
$var wire 1 Y a $end
$var wire 1 Z b $end
$var wire 1 ] sum $end
$var wire 1 ^ cout $end
$upscope $end
$scope module ha2 $end
$var wire 1 R a $end
$var wire 1 ] b $end
$var wire 1 [ sum $end
$var wire 1 \ cout $end
$upscope $end
$upscope $end
$scope module fa3 $end
$var wire 1 _ a $end
$var wire 1 ` b $end
$var wire 1 Q cin $end
$var wire 1 P cout $end
$var wire 1 a sum $end
$var wire 1 b ha2_cout $end
$var wire 1 c ha1_sum $end
$var wire 1 d ha1_cout $end
$scope module ha1 $end
$var wire 1 _ a $end
$var wire 1 ` b $end
$var wire 1 c sum $end
$var wire 1 d cout $end
$upscope $end
$scope module ha2 $end
$var wire 1 Q a $end
$var wire 1 c b $end
$var wire 1 a sum $end
$var wire 1 b cout $end
$upscope $end
$upscope $end
$scope module fa4 $end
$var wire 1 e a $end
$var wire 1 f b $end
$var wire 1 P cin $end
$var wire 1 , cout $end
$var wire 1 g sum $end
$var wire 1 h ha2_cout $end
$var wire 1 i ha1_sum $end
$var wire 1 j ha1_cout $end
$scope module ha1 $end
$var wire 1 e a $end
$var wire 1 f b $end
$var wire 1 i sum $end
$var wire 1 j cout $end
$upscope $end
$scope module ha2 $end
$var wire 1 P a $end
$var wire 1 i b $end
$var wire 1 g sum $end
$var wire 1 h cout $end
$upscope $end
$upscope $end
$upscope $end
$scope module a3 $end
$var wire 4 k a [3:0] $end
$var wire 4 l b [3:0] $end
$var wire 1 m cin $end
$var wire 4 n sum [3:0] $end
$var wire 1 o fa3_out $end
$var wire 1 p fa2_out $end
$var wire 1 q fa1_out $end
$var wire 1 + cout $end
$scope module fa1 $end
$var wire 1 r a $end
$var wire 1 s b $end
$var wire 1 m cin $end
$var wire 1 q cout $end
$var wire 1 t sum $end
$var wire 1 u ha2_cout $end
$var wire 1 v ha1_sum $end
$var wire 1 w ha1_cout $end
$scope module ha1 $end
$var wire 1 r a $end
$var wire 1 s b $end
$var wire 1 v sum $end
$var wire 1 w cout $end
$upscope $end
$scope module ha2 $end
$var wire 1 m a $end
$var wire 1 v b $end
$var wire 1 t sum $end
$var wire 1 u cout $end
$upscope $end
$upscope $end
$scope module fa2 $end
$var wire 1 x a $end
$var wire 1 y b $end
$var wire 1 q cin $end
$var wire 1 p cout $end
$var wire 1 z sum $end
$var wire 1 { ha2_cout $end
$var wire 1 | ha1_sum $end
$var wire 1 } ha1_cout $end
$scope module ha1 $end
$var wire 1 x a $end
$var wire 1 y b $end
$var wire 1 | sum $end
$var wire 1 } cout $end
$upscope $end
$scope module ha2 $end
$var wire 1 q a $end
$var wire 1 | b $end
$var wire 1 z sum $end
$var wire 1 { cout $end
$upscope $end
$upscope $end
$scope module fa3 $end
$var wire 1 ~ a $end
$var wire 1 !" b $end
$var wire 1 p cin $end
$var wire 1 o cout $end
$var wire 1 "" sum $end
$var wire 1 #" ha2_cout $end
$var wire 1 $" ha1_sum $end
$var wire 1 %" ha1_cout $end
$scope module ha1 $end
$var wire 1 ~ a $end
$var wire 1 !" b $end
$var wire 1 $" sum $end
$var wire 1 %" cout $end
$upscope $end
$scope module ha2 $end
$var wire 1 p a $end
$var wire 1 $" b $end
$var wire 1 "" sum $end
$var wire 1 #" cout $end
$upscope $end
$upscope $end
$scope module fa4 $end
$var wire 1 &" a $end
$var wire 1 '" b $end
$var wire 1 o cin $end
$var wire 1 + cout $end
$var wire 1 (" sum $end
$var wire 1 )" ha2_cout $end
$var wire 1 *" ha1_sum $end
$var wire 1 +" ha1_cout $end
$scope module ha1 $end
$var wire 1 &" a $end
$var wire 1 '" b $end
$var wire 1 *" sum $end
$var wire 1 +" cout $end
$upscope $end
$scope module ha2 $end
$var wire 1 o a $end
$var wire 1 *" b $end
$var wire 1 (" sum $end
$var wire 1 )" cout $end
$upscope $end
$upscope $end
$upscope $end
$scope module cout_mux $end
$var wire 2 ," d [1:0] $end
$var wire 1 - s $end
$var wire 1 " y $end
$upscope $end
$scope module sum_hi_4 $end
$var wire 4 -" d0 [3:0] $end
$var wire 4 ." d1 [3:0] $end
$var wire 1 - s $end
$var wire 4 /" y [3:0] $end
$upscope $end
$upscope $end
$scope begin $ivl_for_loop0 $end
$var integer 32 0" i [31:0] $end
$upscope $end
$upscope $end
$enddefinitions $end
$comment Show the parameter values. $end
$dumpall
$end
#0
$dumpvars
b0 0"
b1010 /"
b1011 ."
b1010 -"
b0 ,"
0+"
1*"
0)"
1("
1'"
0&"
0%"
0$"
0#"
0""
0!"
0~
0}
1|
0{
1z
0y
1x
0w
0v
0u
1t
0s
0r
0q
0p
0o
b1011 n
1m
b1000 l
b10 k
0j
1i
0h
1g
1f
0e
0d
0c
0b
0a
0`
0_
0^
1]
0\
1[
0Z
1Y
0X
0W
0V
0U
0T
0S
0R
0Q
0P
b1010 O
0N
b1000 M
b10 L
0K
0J
0I
0H
0G
0F
0E
1D
0C
1B
0A
1@
0?
0>
0=
0<
0;
0:
09
18
07
16
15
04
03
02
01
b101 0
b1 /
b100 .
0-
0,
0+
b1010 *
b1011 )
b10100101 (
b10000001 '
b100100 &
0%
b10000001 $
b100100 #
0"
b10100101 !
$end
#10
1-
1I
11
0B
1C
12
b111 /"
0H
0g
0("
1=
b110 *
b110 O
b110 -"
1a
b111 )
b111 n
b111 ."
1""
1J
0i
0*"
08
19
1>
1c
1$"
13
1A
1G
0f
0'"
14
1:
0@
1_
1~
b1110001 !
b1110001 (
b1 0
16
07
b1101 /
b0 M
b0 l
b11 .
b110 L
b110 k
1%
b1101 $
b1101 '
b1100011 #
b1100011 &
b1 0"
#20
1("
1o
11
0""
1#"
0B
1C
1p
12
0z
1{
0<
1=
0-
b111 /"
1q
06
17
13
b1111000 !
b1111000 (
b1000 0
1H
0I
b111 *
b111 O
b111 -"
1U
b1000 )
b1000 n
b1000 ."
0t
1u
18
09
0J
1W
1v
05
1;
0A
0G
1T
1s
0:
1@
b10 /
b1 M
b1 l
b101 .
b10010 $
b10010 '
b1100101 #
b1100101 &
b10 0"
#30
b1000 /"
1-
1B
0C
b10000100 !
b10000100 (
b100 0
0H
1I
0D
1E
1J
1A
1Z
1`
1y
1!"
1F
0Y
0_
0x
0~
b110 /
b111 M
b111 l
b1101 .
b0 L
b0 k
b1110110 $
b1110110 '
b1101 #
b1101 &
b11 0"
#40
0("
0o
1""
0#"
0p
0B
1z
0{
1"
02
b111 /"
0q
1<
0=
b1111010 !
b1111010 (
b1010 0
1H
0I
b110 *
b110 O
b110 -"
0U
1,
b111 )
b111 n
b111 ."
1t
0u
b11 ,"
1+
0>
0J
1K
0W
1j
0v
1+"
0;
1G
0T
0Z
0`
1f
0s
0y
0!"
1'"
1Y
1_
1e
1x
1~
1&"
b1100 /
b1000 M
b1000 l
b1110 L
b1110 k
b10001100 $
b10001100 '
b11101101 #
b11101101 &
b100 0"
#50
1g
1("
b1000 /"
0a
1P
0""
1o
0-
b1000 *
b1000 O
b1000 -"
0[
b1001 )
b1001 n
b1001 ."
0z
0c
1d
0$"
1%"
1>
0K
0]
0|
03
15
0G
1`
1!"
04
1:
0F
0Y
0x
b10001011 !
b10001011 (
b1011 0
16
07
b101 /
b1100 M
b1100 l
b110 .
b1100 L
b1100 k
0%
b11000101 $
b11000101 '
b11000110 #
b11000110 &
b101 0"
#60
1B
1"
1z
12
1a
b101 /"
1q
1""
0<
1=
1U
1Q
b101 *
b101 O
b101 -"
0g
1h
1,
0t
1u
1p
b110 )
b110 n
b110 ."
0("
1)"
b11 ,"
1+
b1011100 !
b1011100 (
b1100 0
06
13
1W
1^
1i
0j
1v
1}
1*"
0+"
08
19
1;
1T
1Z
0f
1s
1y
0'"
14
0:
1Y
1x
b111 /
b111 M
b111 l
b101 .
b1110 L
b1110 k
b1110111 $
b1110111 '
b11100101 #
b11100101 &
b110 0"
#70
0g
1("
1-
b1000 /"
16
03
0B
1C
11
0h
0)"
0<
0=
b10000001 !
b10000001 (
b1 0
0H
1I
1[
0Q
b111 *
b111 O
b111 -"
1a
0b
0P
0z
1{
1p
b1000 )
b1000 n
b1000 ."
0""
1#"
1o
18
09
1D
0E
0i
1j
0*"
1+"
0>
1?
1J
1]
0^
1c
0d
1|
0}
1$"
0%"
05
0A
1f
1'"
1:
1F
0Y
0_
0x
0~
b10 /
b1111 M
b1111 l
b1111 .
b1000 L
b1000 k
b11110010 $
b11110010 '
b10001111 #
b10001111 &
b111 0"
#80
0-
0p
1H
0I
1z
0{
01
0q
1B
0C
1g
b1010 /"
0U
1t
0u
02
b1010 *
b1010 O
b1010 -"
0a
1P
b1011 )
b1011 n
b1011 ."
0""
0#"
1<
0W
0v
0?
0c
1d
0$"
1%"
13
15
0;
1A
0T
0Z
0s
0y
04
0:
0@
1Y
1_
1x
1~
b10101110 !
b10101110 (
b1110 0
06
17
b101 /
b1100 M
b1100 l
b1000 .
b1110 L
b1110 k
1%
b11000101 $
b11000101 '
b11101000 #
b11101000 &
b1000 0"
#90
0"
1a
1""
b1110 /"
1q
1-
0[
1Q
0,
1z
1p
b0 ,"
0+
0B
11
b1101 *
b1101 O
b1101 -"
1U
0P
b1110 )
b1110 n
b1110 ."
0t
1u
0o
1<
0J
1K
0]
1^
1i
0j
0|
1}
1*"
0+"
08
19
0D
1E
1W
0d
1v
0%"
13
1G
1Z
0`
0f
1y
0!"
0'"
14
1@
1S
0_
1r
0~
b11101010 !
b11101010 (
b1010 0
06
07
b1101 /
b10 M
b10 l
b1101 .
b1011 L
b1011 k
0%
b101101 $
b101101 '
b10111101 #
b10111101 &
b1001 0"
#100
0<
1B
0P
0q
0o
b110 /"
16
03
12
1[
0Q
1z
0{
0p
01
b1101101 !
b1101101 (
b1101 0
1H
0I
0-
0U
1a
0b
b110 *
b110 O
b110 -"
0g
1t
0u
1""
0#"
b111 )
b111 n
b111 ."
0("
18
09
1?
1]
0^
1|
0}
0E
1J
0K
0W
1c
0i
0v
1$"
0*"
05
1;
0A
0Z
0y
1:
0@
0F
0S
1_
0e
0r
1~
0&"
b1010 /
b0 M
b0 l
b11 .
b110 L
b110 k
b1010 $
b1010 '
b1100011 #
b1100011 &
b1010 0"
#110
0B
b1100 /"
0[
1Q
1g
0z
1p
1("
06
b11001010 !
b11001010 (
b1010 0
1<
02
b1100 *
b1100 O
b1100 -"
1a
b1101 )
b1101 n
b1101 ."
1""
0]
1^
1i
0|
1}
1*"
08
1>
0?
0c
0$"
1Z
1f
1y
1'"
04
0:
0_
0~
b1010 M
b1010 l
b0 .
b10 L
b10 k
b10101010 $
b10101010 '
b100000 #
b100000 &
b1011 0"
#120
11
b1010 /"
1[
1z
1C
b1010 *
b1010 O
b1010 -"
0a
b1011 )
b1011 n
b1011 ."
0""
16
1H
1R
1q
0<
12
b10101001 !
b10101001 (
b1001 0
0B
0Q
0p
18
0J
1X
1w
0>
1?
1D
0^
0}
15
0G
1T
0Z
0f
1s
0y
0'"
1:
1@
1S
0Y
1e
1r
0x
1&"
b11 /
b1 M
b1 l
b110 .
b1001 L
b1001 k
b10011 $
b10011 '
b10010110 #
b10010110 &
b1100 0"
#130
0a
1""
0-
0Q
1p
1<
01
b1011 /"
1H
0I
1U
0R
1[
0\
1P
0t
1u
1q
0z
1{
1o
06
13
b10111110 !
b10111110 (
b1110 0
1B
0C
b1011 *
b1011 O
b1011 -"
1g
b1100 )
b1100 n
b1100 ."
1("
1J
1W
0X
1]
1d
1v
0w
1|
1%"
08
19
0D
0i
0*"
1G
0T
1Z
1`
0s
1y
1!"
14
0@
1_
0e
1~
0&"
b1011 /
b110 M
b110 l
b11 .
b101 L
b101 k
b1101011 $
b1101011 '
b1010011 #
b1010011 &
b1101 0"
#140
0""
1-
0p
0H
1I
1z
0{
11
0<
b1011 /"
0q
0B
1C
03
b1010 *
b1010 O
b1010 -"
0U
0P
b1011 )
b1011 n
b1011 ."
1t
0u
0o
1D
1i
1*"
09
0W
0d
0v
0%"
05
1A
0`
1f
0!"
1'"
04
0S
0_
0r
0~
b10110001 !
b10110001 (
b1 0
16
b1110 /
b1010 M
b1010 l
b10 .
b0 L
b0 k
1%
b10101110 $
b10101110 '
b10 #
b10 &
b1110 0"
#150
b11 0
1<
b11110011 !
b11110011 (
b1111 /"
13
b1110 *
b1110 O
b1110 -"
1a
b1111 )
b1111 n
b1111 ."
1""
19
1c
1$"
15
0A
0G
0f
0'"
14
1@
1F
1_
1e
1~
1&"
b11 /
b10 M
b10 l
b1111 .
b1100 L
b1100 k
b100011 $
b100011 '
b11001111 #
b11001111 &
b1111 0"
#160
1"
b10 ,"
1+
0("
1)"
1o
0""
1#"
1p
01
0z
1{
1B
0C
b0 /"
1q
02
b111 !
b111 (
b111 0
0H
0I
b1111 *
b1111 O
b1111 -"
1U
b0 )
b0 n
b0 ."
0t
1u
03
1>
0?
0J
1K
1W
1v
09
05
0;
1A
1G
1T
1s
04
0@
b1100 /
b11 M
b11 l
b1010 .
b111100 $
b111100 '
b11001010 #
b11001010 &
b10000 0"
#170
b0 ,"
0+
1("
0)"
0o
1""
0#"
0"
0q
b1100 /"
0p
0B
1H
0-
0U
b1100 *
b1100 O
b1100 -"
0[
1t
0u
b1101 )
b1101 n
b1101 ."
0z
0{
18
0D
1J
0K
0W
0]
0v
0|
15
0A
0G
0T
0Z
1`
0s
0y
1!"
0_
0~
b11001011 !
b11001011 (
b1011 0
16
b1 /
b100 M
b100 l
b1000 L
b1000 k
0%
b1000001 $
b1000001 '
b10001010 #
b10001010 &
b10001 0"
#180
1"
b10 ,"
1+
0("
1)"
1o
0""
1#"
1p
1{
b0 /"
1q
0H
1-
1U
b1111 *
b1111 O
b1111 -"
1[
0t
1u
b0 )
b0 n
b0 ."
0z
0J
1K
0>
1W
1]
1v
1|
13
1G
0`
1f
0!"
1'"
0:
1S
1Y
1_
0e
1r
1x
1~
0&"
b10 !
b10 (
b10 0
06
17
b1001 /
b1000 M
b1000 l
b1000 .
b111 L
b111 k
1%
b10001001 $
b10001001 '
b1111000 #
b1111000 &
b10010 0"
#190
0<
03
1B
1H
b111 /"
b1111101 !
b1111101 (
b1101 0
16
07
12
11
0-
b111 *
b111 O
b111 -"
0g
b11 ,"
1,
b1000 )
b1000 n
b1000 ."
1("
0)"
08
1?
1E
0K
0i
1j
0*"
1+"
05
1;
1A
0G
1`
1!"
1:
1@
0F
0_
1e
0~
1&"
b110 /
b1100 M
b1100 l
b110 .
b1011 L
b1011 k
b11000110 $
b11000110 '
b10110110 #
b10110110 &
b10011 0"
#200
0H
0"
b1110 /"
0o
01
1-
0[
1Q
1a
b1101 *
b1101 O
b1101 -"
1g
0,
1z
0{
1""
0#"
b1110 )
b1110 n
b1110 ."
1("
0)"
b0 ,"
0+
1<
02
1D
0E
1K
0]
1^
0c
1i
0j
0|
1}
0$"
1*"
0+"
1>
0?
0A
1G
1Z
0`
0f
1y
0!"
0'"
0:
1F
b11100110 !
b11100110 (
b110 0
06
b1010 /
b10 M
b10 l
b1100 .
0%
b101010 $
b101010 '
b10111100 #
b10111100 &
b10100 0"
#210
0"
0,
b10 ,"
1+
1g
0h
0("
1)"
0P
b1111 /"
1o
13
1<
1[
0Q
0z
1{
1p
0-
b1111 *
b1111 O
b1111 -"
1a
0b
b0 )
b0 n
b0 ."
0""
1#"
19
0>
1]
0^
1|
0}
0K
1c
1$"
15
0;
1A
0G
0Z
1f
0y
1'"
14
0@
0F
1_
0e
1~
0&"
b11110111 !
b11110111 (
b111 0
16
b101 /
b1000 M
b1000 l
b1 .
b111 L
b111 k
1%
b10000101 $
b10000101 '
b1110001 #
b1110001 &
b10101 0"
#220
b111 /"
0<
0"
b0 ,"
0+
0o
03
12
1B
1-
0U
1R
1[
1Q
0g
1t
0u
1z
0{
0("
0)"
b110 *
b110 O
b110 -"
1a
b111 )
b111 n
b111 ."
1""
0#"
18
09
1?
0D
1K
0W
1X
0]
1^
0i
0v
1w
0|
1}
0*"
0c
0$"
05
1;
0A
1G
1T
1Z
0f
1s
1y
0'"
1:
1F
0_
0~
b1110101 !
b1110101 (
b101 0
16
b1010 /
b11 M
b11 l
b1011 .
b11 L
b11 k
0%
b111010 $
b111010 '
b111011 #
b111011 &
b10110 0"
#230
1"
1,
b11 ,"
1+
1h
1)"
1P
1o
0H
0a
1b
0""
1#"
01
b0 /"
0g
0("
02
1B
0C
0-
b0 *
b0 O
b0 -"
0[
1\
1Q
b1 )
b1 n
b1 ."
0z
1{
1p
1<
08
19
1c
1i
1$"
1*"
0?
1D
0K
1]
0^
1|
0}
13
15
0;
0G
1`
1f
1!"
1'"
0:
1@
0F
0Y
0x
b111 !
b111 (
b111 0
16
07
b1 /
b1111 M
b1111 l
b101 .
b1 L
b1 k
1%
b11110001 $
b11110001 '
b10101 #
b10101 &
b10111 0"
#240
0-
0I
0"
01
1B
0C
0Q
0p
0,
b0 ,"
0+
02
1[
0\
b1010 /"
1z
0{
1H
1g
0h
1("
0)"
03
b10101111 !
b10101111 (
b1111 0
1<
0=
0R
b1010 *
b1010 O
b1010 -"
0a
0b
0q
b1011 )
b1011 n
b1011 ."
0""
0#"
1J
0i
0*"
09
1>
0X
0c
1d
0w
0$"
1%"
05
1A
1G
0T
0Z
0f
0s
0y
0'"
04
1:
0@
0S
1Y
1_
0r
1x
1~
b1100 /
b100 M
b100 l
b10 .
b110 L
b110 k
b1001100 $
b1001100 '
b1100010 #
b1100010 &
b11000 0"
#250
1#"
1p
0z
1{
1"
1q
b1000 /"
0g
1("
1U
1,
0t
1u
b11 ,"
1+
0H
1-
b111 *
b111 O
b111 -"
1a
0P
b1000 )
b1000 n
b1000 ."
0""
1o
1W
1j
1v
1+"
18
0J
1K
1c
0d
1$"
0%"
0A
1T
1Z
1f
1s
1y
1'"
14
1@
1F
0Y
0_
1e
0x
0~
1&"
b10000111 !
b10000111 (
b111 0
16
b1000 /
b1111 M
b1111 l
b1111 .
b1000 L
b1000 k
0%
b11111000 $
b11111000 '
b10001111 #
b10001111 &
b11001 0"
#260
0o
1""
0#"
0"
1H
0p
b1111 /"
b11111011 !
b11111011 (
b1011 0
0B
11
1g
0,
1z
0{
1("
0)"
b0 ,"
0+
b1110 *
b1110 O
b1110 -"
0U
1R
b1111 )
b1111 n
b1111 ."
1t
0u
0D
1E
0]
1i
0j
0|
1*"
0+"
0W
1X
0v
1w
1A
0Z
0f
0y
0'"
1S
1r
b1100 /
b101 M
b101 l
b1001 L
b1001 k
b1011100 $
b1011100 '
b10011111 #
b10011111 &
b11010 0"
#270
b1101 /"
0H
b1100 *
b1100 O
b1100 -"
0[
b1101 )
b1101 n
b1101 ."
0z
06
13
b11010010 !
b11010010 (
b10 0
1<
01
0R
0q
08
19
0>
0E
0X
0w
15
0A
0T
0s
0:
0@
0S
0r
b1001 /
b100 M
b100 l
b1001 .
b1000 L
b1000 k
b1001001 $
b1001001 '
b10001001 #
b10001001 &
b11011 0"
#280
1H
1"
11
1C
1,
b11 ,"
1+
1[
1z
12
0g
1h
b10 /"
0("
1)"
1R
1q
0<
1=
0B
0-
b10 *
b10 O
b10 -"
0a
1P
b11 )
b11 n
b11 ."
0""
1o
1X
1w
1>
1D
0K
0c
1d
0$"
1%"
0G
1T
1s
1:
1@
0F
1S
1_
1r
1~
b101001 !
b101001 (
b1001 0
16
b1 /
b101 M
b101 l
b111 .
b1101 L
b1101 k
1%
b1010001 $
b1010001 '
b11010111 #
b11010111 &
b11100 0"
#290
01
0"
1B
0C
02
0,
b0 ,"
0+
1<
0=
0-
0[
b1100 /"
1g
0h
0z
1("
0)"
03
b11001111 !
b11001111 (
b1111 0
1H
0I
0R
b1100 *
b1100 O
b1100 -"
1a
0P
0q
b1101 )
b1101 n
b1101 ."
1""
0o
09
1J
0X
1c
0d
0w
1$"
0%"
05
1;
0T
1f
0s
1'"
04
0:
1F
0S
0_
0e
0r
0~
0&"
b10 /
b1100 M
b1100 l
b1100 .
b0 L
b0 k
b11000010 $
b11000010 '
b1100 #
b1100 &
b11101 0"
#300
12
1-
1P
1o
0<
1=
0H
1I
1[
0a
1b
b1011 /"
1z
0""
1#"
13
b10110101 !
b10110101 (
b101 0
1B
11
1R
1Q
b1010 *
b1010 O
b1010 -"
1g
1q
1p
b1011 )
b1011 n
b1011 ."
1("
19
0D
1E
1X
1^
0i
1w
1}
0*"
15
0;
1A
1G
1T
1Z
0`
0f
1s
1y
0!"
0'"
14
1:
0F
1S
1Y
1_
1r
1x
1~
b1101 /
b11 M
b11 l
b111 .
b111 L
b111 k
b111101 $
b111101 '
b1110111 #
b1110111 &
b11110 0"
#310
1B
12
0[
1z
b1110 /"
0<
1=
1U
0R
b1101 *
b1101 O
b1101 -"
1a
0b
0t
1u
1q
b1110 )
b1110 n
b1110 ."
1""
0#"
06
17
13
b11101100 !
b11101100 (
b1100 0
1H
0I
1W
0X
0c
1d
1v
0w
0$"
1%"
18
09
0J
1K
0T
1`
0s
1!"
04
1F
b110 M
b110 l
b1110 .
b1101101 $
b1101101 '
b1111110 #
b1111110 &
b11111 0"
