8_bit_CSA/mux2.sv
module mux2 (
    input  logic [1:0] d,
    input  logic       s,
    output logic       y
);

  assign y = s ? d[1] : d[0];

  // always_comb begin : mux
  //   if (s) begin
  //     y = d[1];
  //   end else begin
  //     y = d[0];
  //   end
  // end
endmodule

8_bit_CSA/mux2_tb.sv
module mux2_tb;
  logic [1:0] d;
  logic       s;
  logic       y;

  mux2 uut (
      .d(d),
      .s(s),
      .y(y)
  );

  initial begin
    $dumpfile("mux2.vcd");
    $dumpvars(0, mux2_tb);
    $display("d[1]  d[0]  sel |  y");
    $display("---------------------");
    for (int i = 0; i < 2 ** 3; i++) begin
      {d[1], d[0], s} = i[2:0];
      #5;
      $display("%0d  %0d  %0d |  %0d", d[1], d[0], s, y);
    end
  end
endmodule

8_bit_CSA/mux2.vcd
$date
	Wed Jun  4 15:02:24 2025
$end
$version
	Icarus Verilog
$end
$timescale
	1s
$end
$scope module mux2_tb $end
$var wire 1 ! y $end
$var reg 2 " d [1:0] $end
$var reg 1 # s $end
$scope module uut $end
$var wire 2 $ d [1:0] $end
$var wire 1 # s $end
$var wire 1 ! y $end
$upscope $end
$scope begin $ivl_for_loop0 $end
$var integer 32 % i [31:0] $end
$upscope $end
$upscope $end
$enddefinitions $end
$comment Show the parameter values. $end
$dumpall
$end
#0
$dumpvars
b0 %
b0 $
0#
b0 "
0!
$end
#5
1#
b1 %
#10
1!
b1 "
b1 $
0#
b10 %
#15
0!
1#
b11 %
#20
0!
b10 "
b10 $
0#
b100 %
#25
1!
1#
b101 %
#30
1!
b11 "
b11 $
0#
b110 %
#35
1#
b111 %
#40
b1000 %
