3x3_Mult/half_adder.sv
module half_adder (
    input  logic a,
    input  logic b,
    output logic sum,
    output logic cout
);
  assign {cout, sum} = a + b;
endmodule

full_adder.sv
module full_adder (
    input  logic a,
    input  logic b,
    input  logic cin,
    output logic cout,
    output logic sum
);
  logic ha1_sum, ha1_cout, ha2_cout;

  half_adder ha1 (
      .a(a),
      .b(b),
      .sum(ha1_sum),
      .cout(ha1_cout)
  );
  half_adder ha2 (
      .a(cin),
      .b(ha1_sum),
      .sum(sum),
      .cout(ha2_cout)
  );

  assign cout = ha2_cout | ha1_cout;
endmodule

8_bit_CSA/rca4.sv
`include "../3x3_Mult/half_adder.sv"
`include "../3x3_Mult/full_adder.sv"

module rca4 (
    input  logic [3:0] a,
    input  logic [3:0] b,
    input  logic       cin,
    output logic       cout,
    output logic [3:0] sum
);

  logic fa1_out, fa2_out, fa3_out;

  full_adder fa1 (
      .a(a[0]),
      .b(b[0]),
      .cin(cin),
      .cout(fa1_out),
      .sum(sum[0])
  );
  full_adder fa2 (
      .a(a[1]),
      .b(b[1]),
      .cin(fa1_out),
      .cout(fa2_out),
      .sum(sum[1])
  );
  full_adder fa3 (
      .a(a[2]),
      .b(b[2]),
      .cin(fa2_out),
      .cout(fa3_out),
      .sum(sum[2])
  );
  full_adder fa4 (
      .a(a[3]),
      .b(b[3]),
      .cin(fa3_out),
      .cout(cout),
      .sum(sum[3])
  );
endmodule

8_bit_CSA/rca4_tb.sv
module rca4_tb;
  logic [3:0] a;
  logic [3:0] b;
  logic       cin;
  logic       cout;
  logic [3:0] sum;

  rca4 uut (
      .a(a),
      .b(b),
      .cin(cin),
      .cout(cout),
      .sum(sum)
  );

  initial begin
    $dumpfile("rca4.vcd");
    $dumpvars(0, rca4_tb);
    $display("a   b   cin | cout sum");
    $display("------------------------");
    for (int i = 0; i < 2 ** $size(a); i++) begin
      for (int j = 0; j < 2 ** $size(b); j++) begin
        a   = i;
        b   = j;
        cin = 0;
        #5;
        cin = 1;
        #10;
        $display("%0d   %0d   %0d | %0d   %0d", a, b, cin, cout, sum);
      end
    end
    $finish;
  end

endmodule

8_bit_CSA/rca4.vcd
$date
	Tue Jun  3 21:00:14 2025
$end
$version
	Icarus Verilog
$end
$timescale
	1s
$end
$scope module rca4_tb $end
$var wire 4 ! sum [3:0] $end
$var wire 1 " cout $end
$var reg 4 # a [3:0] $end
$var reg 4 $ b [3:0] $end
$var reg 1 % cin $end
$scope module uut $end
$var wire 4 & a [3:0] $end
$var wire 4 ' b [3:0] $end
$var wire 1 % cin $end
$var wire 4 ( sum [3:0] $end
$var wire 1 ) fa3_out $end
$var wire 1 * fa2_out $end
$var wire 1 + fa1_out $end
$var wire 1 " cout $end
$scope module fa1 $end
$var wire 1 , a $end
$var wire 1 - b $end
$var wire 1 % cin $end
$var wire 1 + cout $end
$var wire 1 . sum $end
$var wire 1 / ha2_cout $end
$var wire 1 0 ha1_sum $end
$var wire 1 1 ha1_cout $end
$scope module ha1 $end
$var wire 1 , a $end
$var wire 1 - b $end
$var wire 1 0 sum $end
$var wire 1 1 cout $end
$upscope $end
$scope module ha2 $end
$var wire 1 % a $end
$var wire 1 0 b $end
$var wire 1 . sum $end
$var wire 1 / cout $end
$upscope $end
$upscope $end
$scope module fa2 $end
$var wire 1 2 a $end
$var wire 1 3 b $end
$var wire 1 + cin $end
$var wire 1 * cout $end
$var wire 1 4 sum $end
$var wire 1 5 ha2_cout $end
$var wire 1 6 ha1_sum $end
$var wire 1 7 ha1_cout $end
$scope module ha1 $end
$var wire 1 2 a $end
$var wire 1 3 b $end
$var wire 1 6 sum $end
$var wire 1 7 cout $end
$upscope $end
$scope module ha2 $end
$var wire 1 + a $end
$var wire 1 6 b $end
$var wire 1 4 sum $end
$var wire 1 5 cout $end
$upscope $end
$upscope $end
$scope module fa3 $end
$var wire 1 8 a $end
$var wire 1 9 b $end
$var wire 1 * cin $end
$var wire 1 ) cout $end
$var wire 1 : sum $end
$var wire 1 ; ha2_cout $end
$var wire 1 < ha1_sum $end
$var wire 1 = ha1_cout $end
$scope module ha1 $end
$var wire 1 8 a $end
$var wire 1 9 b $end
$var wire 1 < sum $end
$var wire 1 = cout $end
$upscope $end
$scope module ha2 $end
$var wire 1 * a $end
$var wire 1 < b $end
$var wire 1 : sum $end
$var wire 1 ; cout $end
$upscope $end
$upscope $end
$scope module fa4 $end
$var wire 1 > a $end
$var wire 1 ? b $end
$var wire 1 ) cin $end
$var wire 1 " cout $end
$var wire 1 @ sum $end
$var wire 1 A ha2_cout $end
$var wire 1 B ha1_sum $end
$var wire 1 C ha1_cout $end
$scope module ha1 $end
$var wire 1 > a $end
$var wire 1 ? b $end
$var wire 1 B sum $end
$var wire 1 C cout $end
$upscope $end
$scope module ha2 $end
$var wire 1 ) a $end
$var wire 1 B b $end
$var wire 1 @ sum $end
$var wire 1 A cout $end
$upscope $end
$upscope $end
$upscope $end
$scope begin $ivl_for_loop0 $end
$var integer 32 D i [31:0] $end
$scope begin $ivl_for_loop1 $end
$var integer 32 E j [31:0] $end
$upscope $end
$upscope $end
$upscope $end
$enddefinitions $end
$comment Show the parameter values. $end
$dumpall
$end
#0
$dumpvars
b0 E
b0 D
0C
0B
0A
0@
0?
0>
0=
0<
0;
0:
09
08
07
06
05
04
03
02
01
00
0/
0.
0-
0,
0+
0*
0)
b0 (
b0 '
b0 &
0%
b0 $
b0 #
0"
b0 !
$end
#5
b1 !
b1 (
1.
1%
#15
10
b1 !
b1 (
1.
1-
0%
b1 $
b1 '
b1 E
#20
14
1+
b10 !
b10 (
0.
1/
1%
#30
0+
00
16
b10 !
b10 (
0.
0/
0-
13
0%
b10 $
b10 '
b10 E
#35
b11 !
b11 (
1.
1%
#45
10
b11 !
b11 (
1.
1-
0%
b11 $
b11 '
b11 E
#50
1:
1*
04
15
1+
b100 !
b100 (
0.
1/
1%
#60
0@
0*
0)
05
1:
0;
0+
00
06
1<
b100 !
b100 (
0.
0/
0-
03
19
0%
b100 $
b100 '
b100 E
#65
b101 !
b101 (
1.
1%
#75
10
b101 !
b101 (
1.
1-
0%
b101 $
b101 '
b101 E
#80
14
1+
b110 !
b110 (
0.
1/
1%
#90
0+
00
16
b110 !
b110 (
0.
0/
0-
13
0%
b110 $
b110 '
b110 E
#95
b111 !
b111 (
1.
1%
#105
10
b111 !
b111 (
1.
1-
0%
b111 $
b111 '
b111 E
#110
1@
1)
0:
1;
1*
04
15
1+
b1000 !
b1000 (
0.
1/
1%
#120
0*
0)
0"
05
0:
0;
1@
0A
0+
00
06
0<
1B
b1000 !
b1000 (
0.
0/
0-
03
09
1?
0%
b1000 $
b1000 '
b1000 E
#125
b1001 !
b1001 (
1.
1%
#135
10
b1001 !
b1001 (
1.
1-
0%
b1001 $
b1001 '
b1001 E
#140
14
1+
b1010 !
b1010 (
0.
1/
1%
#150
0+
00
16
b1010 !
b1010 (
0.
0/
0-
13
0%
b1010 $
b1010 '
b1010 E
#155
b1011 !
b1011 (
1.
1%
#165
10
b1011 !
b1011 (
1.
1-
0%
b1011 $
b1011 '
b1011 E
#170
1:
1*
04
15
1+
b1100 !
b1100 (
0.
1/
1%
#180
0"
1@
0A
0*
0)
05
1:
0;
0+
00
06
1<
b1100 !
b1100 (
0.
0/
0-
03
19
0%
b1100 $
b1100 '
b1100 E
#185
b1101 !
b1101 (
1.
1%
#195
10
b1101 !
b1101 (
1.
1-
0%
b1101 $
b1101 '
b1101 E
#200
14
1+
b1110 !
b1110 (
0.
1/
1%
#210
0+
00
16
b1110 !
b1110 (
0.
0/
0-
13
0%
b1110 $
b1110 '
b1110 E
#215
b1111 !
b1111 (
1.
1%
#225
10
b1111 !
b1111 (
1.
1-
0%
b1111 $
b1111 '
b1111 E
#230
1"
0@
1A
1)
0:
1;
1*
04
15
1+
b0 !
b0 (
0.
1/
1%
#240
0*
0)
0"
05
0:
0;
0@
0A
0+
06
0<
0B
b1 !
b1 (
1.
0/
0-
03
09
0?
1,
0%
b0 $
b0 '
b1 #
b1 &
b1 D
b0 E
#245
14
1+
b10 !
b10 (
0.
1/
1%
#255
00
11
b10 !
b10 (
0.
0/
1-
0%
b1 $
b1 '
b1 E
#260
b11 !
b11 (
1.
1%
#270
0:
0*
0+
14
05
10
01
16
b11 !
b11 (
1.
0-
13
0%
b10 $
b10 '
b10 E
#275
1:
1*
04
15
1+
b100 !
b100 (
0.
1/
1%
#285
00
11
b100 !
b100 (
0.
0/
1-
0%
b11 $
b11 '
b11 E
#290
b101 !
b101 (
1.
1%
#300
0@
0*
0)
0+
04
05
1:
0;
10
01
06
1<
b101 !
b101 (
1.
0-
03
19
0%
b100 $
b100 '
b100 E
#305
14
1+
b110 !
b110 (
0.
1/
1%
#315
00
11
b110 !
b110 (
0.
0/
1-
0%
b101 $
b101 '
b101 E
#320
b111 !
b111 (
1.
1%
#330
0@
0)
1:
0;
0*
0+
14
05
10
01
16
b111 !
b111 (
1.
0-
13
0%
b110 $
b110 '
b110 E
#335
1@
1)
0:
1;
1*
04
15
1+
b1000 !
b1000 (
0.
1/
1%
#345
00
11
b1000 !
b1000 (
0.
0/
1-
0%
b111 $
b111 '
b111 E
#350
b1001 !
b1001 (
1.
1%
#360
0*
0)
0"
0+
04
05
0:
0;
1@
0A
10
01
06
0<
1B
b1001 !
b1001 (
1.
0-
03
09
1?
0%
b1000 $
b1000 '
b1000 E
#365
14
1+
b1010 !
b1010 (
0.
1/
1%
#375
00
11
b1010 !
b1010 (
0.
0/
1-
0%
b1001 $
b1001 '
b1001 E
#380
b1011 !
b1011 (
1.
1%
#390
0:
0*
0+
14
05
10
01
16
b1011 !
b1011 (
1.
0-
13
0%
b1010 $
b1010 '
b1010 E
#395
1:
1*
04
15
1+
b1100 !
b1100 (
0.
1/
1%
#405
00
11
b1100 !
b1100 (
0.
0/
1-
0%
b1011 $
b1011 '
b1011 E
#410
b1101 !
b1101 (
1.
1%
#420
0"
1@
0A
0*
0)
0+
04
05
1:
0;
10
01
06
1<
b1101 !
b1101 (
1.
0-
03
19
0%
b1100 $
b1100 '
b1100 E
#425
14
1+
b1110 !
b1110 (
0.
1/
1%
#435
00
11
b1110 !
b1110 (
0.
0/
1-
0%
b1101 $
b1101 '
b1101 E
#440
b1111 !
b1111 (
1.
1%
#450
0"
1@
0A
0)
1:
0;
0*
0+
14
05
10
01
16
b1111 !
b1111 (
1.
0-
13
0%
b1110 $
b1110 '
b1110 E
#455
1"
0@
1A
1)
0:
1;
1*
04
15
1+
b0 !
b0 (
0.
1/
1%
#465
00
11
b0 !
b0 (
0.
0/
1-
0%
b1111 $
b1111 '
b1111 E
#470
b1 !
b1 (
1.
1%
#480
0*
0)
0"
14
05
0:
0;
0@
0A
0+
0<
0B
01
b10 !
b10 (
0.
0-
03
09
0?
0,
12
0%
b0 $
b0 '
b10 #
b10 &
b10 D
b0 E
#485
b11 !
b11 (
1.
1%
#495
10
b11 !
b11 (
1.
1-
0%
b1 $
b1 '
b1 E
#500
1:
1*
04
15
1+
b100 !
b100 (
0.
1/
1%
#510
05
0+
00
06
17
b100 !
b100 (
0.
0/
0-
13
0%
b10 $
b10 '
b10 E
#515
b101 !
b101 (
1.
1%
#525
10
b101 !
b101 (
1.
1-
0%
b11 $
b11 '
b11 E
#530
14
1+
b110 !
b110 (
0.
1/
1%
#540
0@
0)
0*
1:
0;
0+
00
16
07
1<
b110 !
b110 (
0.
0/
0-
03
19
0%
b100 $
b100 '
b100 E
#545
b111 !
b111 (
1.
1%
#555
10
b111 !
b111 (
1.
1-
0%
b101 $
b101 '
b101 E
#560
1@
1)
0:
1;
1*
04
15
1+
b1000 !
b1000 (
0.
1/
1%
#570
05
0+
00
06
17
b1000 !
b1000 (
0.
0/
0-
13
0%
b110 $
b110 '
b110 E
#575
b1001 !
b1001 (
1.
1%
#585
10
b1001 !
b1001 (
1.
1-
0%
b111 $
b111 '
b111 E
#590
14
1+
b1010 !
b1010 (
0.
1/
1%
#600
0)
0"
0*
0:
0;
1@
0A
0+
00
16
07
0<
1B
b1010 !
b1010 (
0.
0/
0-
03
09
1?
0%
b1000 $
b1000 '
b1000 E
#605
b1011 !
b1011 (
1.
1%
#615
10
b1011 !
b1011 (
1.
1-
0%
b1001 $
b1001 '
b1001 E
#620
1:
1*
04
15
1+
b1100 !
b1100 (
0.
1/
1%
#630
05
0+
00
06
17
b1100 !
b1100 (
0.
0/
0-
13
0%
b1010 $
b1010 '
b1010 E
#635
b1101 !
b1101 (
1.
1%
#645
10
b1101 !
b1101 (
1.
1-
0%
b1011 $
b1011 '
b1011 E
#650
14
1+
b1110 !
b1110 (
0.
1/
1%
#660
0"
1@
0A
0)
0*
1:
0;
0+
00
16
07
1<
b1110 !
b1110 (
0.
0/
0-
03
19
0%
b1100 $
b1100 '
b1100 E
#665
b1111 !
b1111 (
1.
1%
#675
10
b1111 !
b1111 (
1.
1-
0%
b1101 $
b1101 '
b1101 E
#680
1"
0@
1A
1)
0:
1;
1*
04
15
1+
b0 !
b0 (
0.
1/
1%
#690
05
0+
00
06
17
b0 !
b0 (
0.
0/
0-
13
0%
b1110 $
b1110 '
b1110 E
#695
b1 !
b1 (
1.
1%
#705
10
b1 !
b1 (
1.
1-
0%
b1111 $
b1111 '
b1111 E
#710
14
1+
b10 !
b10 (
0.
1/
1%
#720
0)
0"
0*
0:
0;
0@
0A
0+
16
07
0<
0B
b11 !
b11 (
1.
0/
0-
03
09
0?
1,
0%
b0 $
b0 '
b11 #
b11 &
b11 D
b0 E
#725
1:
1*
04
15
1+
b100 !
b100 (
0.
1/
1%
#735
00
11
b100 !
b100 (
0.
0/
1-
0%
b1 $
b1 '
b1 E
#740
b101 !
b101 (
1.
1%
#750
0+
04
05
10
01
06
17
b101 !
b101 (
1.
0-
13
0%
b10 $
b10 '
b10 E
#755
14
1+
b110 !
b110 (
0.
1/
1%
#765
00
11
b110 !
b110 (
0.
0/
1-
0%
b11 $
b11 '
b11 E
#770
b111 !
b111 (
1.
1%
#780
0@
0)
0+
14
05
0*
1:
0;
10
01
16
07
1<
b111 !
b111 (
1.
0-
03
19
0%
b100 $
b100 '
b100 E
#785
1@
1)
0:
1;
1*
04
15
1+
b1000 !
b1000 (
0.
1/
1%
#795
00
11
b1000 !
b1000 (
0.
0/
1-
0%
b101 $
b101 '
b101 E
#800
b1001 !
b1001 (
1.
1%
#810
0+
04
05
10
01
06
17
b1001 !
b1001 (
1.
0-
13
0%
b110 $
b110 '
b110 E
#815
14
1+
b1010 !
b1010 (
0.
1/
1%
#825
00
11
b1010 !
b1010 (
0.
0/
1-
0%
b111 $
b111 '
b111 E
#830
b1011 !
b1011 (
1.
1%
#840
0)
0"
0+
14
05
0*
0:
0;
1@
0A
10
01
16
07
0<
1B
b1011 !
b1011 (
1.
0-
03
09
1?
0%
b1000 $
b1000 '
b1000 E
#845
1:
1*
04
15
1+
b1100 !
b1100 (
0.
1/
1%
#855
00
11
b1100 !
b1100 (
0.
0/
1-
0%
b1001 $
b1001 '
b1001 E
#860
b1101 !
b1101 (
1.
1%
#870
0+
04
05
10
01
06
17
b1101 !
b1101 (
1.
0-
13
0%
b1010 $
b1010 '
b1010 E
#875
14
1+
b1110 !
b1110 (
0.
1/
1%
#885
00
11
b1110 !
b1110 (
0.
0/
1-
0%
b1011 $
b1011 '
b1011 E
#890
b1111 !
b1111 (
1.
1%
#900
0"
1@
0A
0)
0+
14
05
0*
1:
0;
10
01
16
07
1<
b1111 !
b1111 (
1.
0-
03
19
0%
b1100 $
b1100 '
b1100 E
#905
1"
0@
1A
1)
0:
1;
1*
04
15
1+
b0 !
b0 (
0.
1/
1%
#915
00
11
b0 !
b0 (
0.
0/
1-
0%
b1101 $
b1101 '
b1101 E
#920
b1 !
b1 (
1.
1%
#930
0+
04
05
10
01
06
17
b1 !
b1 (
1.
0-
13
0%
b1110 $
b1110 '
b1110 E
#935
14
1+
b10 !
b10 (
0.
1/
1%
#945
00
11
b10 !
b10 (
0.
0/
1-
0%
b1111 $
b1111 '
b1111 E
#950
b11 !
b11 (
1.
1%
#960
0)
0"
04
1:
0;
0@
0A
0+
0*
0B
01
07
b100 !
b100 (
0.
0-
03
09
0?
0,
02
18
0%
b0 $
b0 '
b100 #
b100 &
b100 D
b0 E
#965
b101 !
b101 (
1.
1%
#975
10
b101 !
b101 (
1.
1-
0%
b1 $
b1 '
b1 E
#980
14
1+
b110 !
b110 (
0.
1/
1%
#990
0+
00
16
b110 !
b110 (
0.
0/
0-
13
0%
b10 $
b10 '
b10 E
#995
b111 !
b111 (
1.
1%
#1005
10
b111 !
b111 (
1.
1-
0%
b11 $
b11 '
b11 E
#1010
1@
1)
0:
1;
1*
04
15
1+
b1000 !
b1000 (
0.
1/
1%
#1020
0*
05
0:
0;
0+
00
06
0<
1=
b1000 !
b1000 (
0.
0/
0-
03
19
0%
b100 $
b100 '
b100 E
#1025
b1001 !
b1001 (
1.
1%
#1035
10
b1001 !
b1001 (
1.
1-
0%
b101 $
b101 '
b101 E
#1040
14
1+
b1010 !
b1010 (
0.
1/
1%
#1050
0+
00
16
b1010 !
b1010 (
0.
0/
0-
13
0%
b110 $
b110 '
b110 E
#1055
b1011 !
b1011 (
1.
1%
#1065
10
b1011 !
b1011 (
1.
1-
0%
b111 $
b111 '
b111 E
#1070
1:
1*
04
15
1+
b1100 !
b1100 (
0.
1/
1%
#1080
0*
0"
05
1:
0;
0)
1@
0A
0+
00
06
1<
0=
1B
b1100 !
b1100 (
0.
0/
0-
03
09
1?
0%
b1000 $
b1000 '
b1000 E
#1085
b1101 !
b1101 (
1.
1%
#1095
10
b1101 !
b1101 (
1.
1-
0%
b1001 $
b1001 '
b1001 E
#1100
14
1+
b1110 !
b1110 (
0.
1/
1%
#1110
0+
00
16
b1110 !
b1110 (
0.
0/
0-
13
0%
b1010 $
b1010 '
b1010 E
#1115
b1111 !
b1111 (
1.
1%
#1125
10
b1111 !
b1111 (
1.
1-
0%
b1011 $
b1011 '
b1011 E
#1130
1"
0@
1A
1)
0:
1;
1*
04
15
1+
b0 !
b0 (
0.
1/
1%
#1140
0*
05
0:
0;
0+
00
06
0<
1=
b0 !
b0 (
0.
0/
0-
03
19
0%
b1100 $
b1100 '
b1100 E
#1145
b1 !
b1 (
1.
1%
#1155
10
b1 !
b1 (
1.
1-
0%
b1101 $
b1101 '
b1101 E
#1160
14
1+
b10 !
b10 (
0.
1/
1%
#1170
0+
00
16
b10 !
b10 (
0.
0/
0-
13
0%
b1110 $
b1110 '
b1110 E
#1175
b11 !
b11 (
1.
1%
#1185
10
b11 !
b11 (
1.
1-
0%
b1111 $
b1111 '
b1111 E
#1190
1:
1*
04
15
1+
b100 !
b100 (
0.
1/
1%
#1200
0*
0"
05
1:
0;
0)
0@
0A
0+
06
1<
0=
0B
b101 !
b101 (
1.
0/
0-
03
09
0?
1,
0%
b0 $
b0 '
b101 #
b101 &
b101 D
b0 E
#1205
14
1+
b110 !
b110 (
0.
1/
1%
#1215
00
11
b110 !
b110 (
0.
0/
1-
0%
b1 $
b1 '
b1 E
#1220
b111 !
b111 (
1.
1%
#1230
0@
0)
1:
0;
0*
0+
14
05
10
01
16
b111 !
b111 (
1.
0-
13
0%
b10 $
b10 '
b10 E
#1235
1@
1)
0:
1;
1*
04
15
1+
b1000 !
b1000 (
0.
1/
1%
#1245
00
11
b1000 !
b1000 (
0.
0/
1-
0%
b11 $
b11 '
b11 E
#1250
b1001 !
b1001 (
1.
1%
#1260
0*
0+
04
05
0:
0;
10
01
06
0<
1=
b1001 !
b1001 (
1.
0-
03
19
0%
b100 $
b100 '
b100 E
#1265
14
1+
b1010 !
b1010 (
0.
1/
1%
#1275
00
11
b1010 !
b1010 (
0.
0/
1-
0%
b101 $
b101 '
b101 E
#1280
b1011 !
b1011 (
1.
1%
#1290
0:
0*
0+
14
05
10
01
16
b1011 !
b1011 (
1.
0-
13
0%
b110 $
b110 '
b110 E
#1295
1:
1*
04
15
1+
b1100 !
b1100 (
0.
1/
1%
#1305
00
11
b1100 !
b1100 (
0.
0/
1-
0%
b111 $
b111 '
b111 E
#1310
b1101 !
b1101 (
1.
1%
#1320
0*
0"
0+
04
05
1:
0;
0)
1@
0A
10
01
06
1<
0=
1B
b1101 !
b1101 (
1.
0-
03
09
1?
0%
b1000 $
b1000 '
b1000 E
#1325
14
1+
b1110 !
b1110 (
0.
1/
1%
#1335
00
11
b1110 !
b1110 (
0.
0/
1-
0%
b1001 $
b1001 '
b1001 E
#1340
b1111 !
b1111 (
1.
1%
#1350
0"
1@
0A
0)
1:
0;
0*
0+
14
05
10
01
16
b1111 !
b1111 (
1.
0-
13
0%
b1010 $
b1010 '
b1010 E
#1355
1"
0@
1A
1)
0:
1;
1*
04
15
1+
b0 !
b0 (
0.
1/
1%
#1365
00
11
b0 !
b0 (
0.
0/
1-
0%
b1011 $
b1011 '
b1011 E
#1370
b1 !
b1 (
1.
1%
#1380
0*
0+
04
05
0:
0;
10
01
06
0<
1=
b1 !
b1 (
1.
0-
03
19
0%
b1100 $
b1100 '
b1100 E
#1385
14
1+
b10 !
b10 (
0.
1/
1%
#1395
00
11
b10 !
b10 (
0.
0/
1-
0%
b1101 $
b1101 '
b1101 E
#1400
b11 !
b11 (
1.
1%
#1410
0:
0*
0+
14
05
10
01
16
b11 !
b11 (
1.
0-
13
0%
b1110 $
b1110 '
b1110 E
#1415
1:
1*
04
15
1+
b100 !
b100 (
0.
1/
1%
#1425
00
11
b100 !
b100 (
0.
0/
1-
0%
b1111 $
b1111 '
b1111 E
#1430
b101 !
b101 (
1.
1%
#1440
0*
0"
14
05
1:
0;
0)
0@
0A
0+
1<
0=
0B
01
b110 !
b110 (
0.
0-
03
09
0?
0,
12
0%
b0 $
b0 '
b110 #
b110 &
b110 D
b0 E
#1445
b111 !
b111 (
1.
1%
#1455
10
b111 !
b111 (
1.
1-
0%
b1 $
b1 '
b1 E
#1460
1@
1)
0:
1;
1*
04
15
1+
b1000 !
b1000 (
0.
1/
1%
#1470
05
0+
00
06
17
b1000 !
b1000 (
0.
0/
0-
13
0%
b10 $
b10 '
b10 E
#1475
b1001 !
b1001 (
1.
1%
#1485
10
b1001 !
b1001 (
1.
1-
0%
b11 $
b11 '
b11 E
#1490
14
1+
b1010 !
b1010 (
0.
1/
1%
#1500
0*
0:
0;
0+
00
16
07
0<
1=
b1010 !
b1010 (
0.
0/
0-
03
19
0%
b100 $
b100 '
b100 E
#1505
b1011 !
b1011 (
1.
1%
#1515
10
b1011 !
b1011 (
1.
1-
0%
b101 $
b101 '
b101 E
#1520
1:
1*
04
15
1+
b1100 !
b1100 (
0.
1/
1%
#1530
05
0+
00
06
17
b1100 !
b1100 (
0.
0/
0-
13
0%
b110 $
b110 '
b110 E
#1535
b1101 !
b1101 (
1.
1%
#1545
10
b1101 !
b1101 (
1.
1-
0%
b111 $
b111 '
b111 E
#1550
14
1+
b1110 !
b1110 (
0.
1/
1%
#1560
0"
0*
1:
0;
0)
1@
0A
0+
00
16
07
1<
0=
1B
b1110 !
b1110 (
0.
0/
0-
03
09
1?
0%
b1000 $
b1000 '
b1000 E
#1565
b1111 !
b1111 (
1.
1%
#1575
10
b1111 !
b1111 (
1.
1-
0%
b1001 $
b1001 '
b1001 E
#1580
1"
0@
1A
1)
0:
1;
1*
04
15
1+
b0 !
b0 (
0.
1/
1%
#1590
05
0+
00
06
17
b0 !
b0 (
0.
0/
0-
13
0%
b1010 $
b1010 '
b1010 E
#1595
b1 !
b1 (
1.
1%
#1605
10
b1 !
b1 (
1.
1-
0%
b1011 $
b1011 '
b1011 E
#1610
14
1+
b10 !
b10 (
0.
1/
1%
#1620
0*
0:
0;
0+
00
16
07
0<
1=
b10 !
b10 (
0.
0/
0-
03
19
0%
b1100 $
b1100 '
b1100 E
#1625
b11 !
b11 (
1.
1%
#1635
10
b11 !
b11 (
1.
1-
0%
b1101 $
b1101 '
b1101 E
#1640
1:
1*
04
15
1+
b100 !
b100 (
0.
1/
1%
#1650
05
0+
00
06
17
b100 !
b100 (
0.
0/
0-
13
0%
b1110 $
b1110 '
b1110 E
#1655
b101 !
b101 (
1.
1%
#1665
10
b101 !
b101 (
1.
1-
0%
b1111 $
b1111 '
b1111 E
#1670
14
1+
b110 !
b110 (
0.
1/
1%
#1680
0"
0*
1:
0;
0)
0@
0A
0+
16
07
1<
0=
0B
b111 !
b111 (
1.
0/
0-
03
09
0?
1,
0%
b0 $
b0 '
b111 #
b111 &
b111 D
b0 E
#1685
1@
1)
0:
1;
1*
04
15
1+
b1000 !
b1000 (
0.
1/
1%
#1695
00
11
b1000 !
b1000 (
0.
0/
1-
0%
b1 $
b1 '
b1 E
#1700
b1001 !
b1001 (
1.
1%
#1710
0+
04
05
10
01
06
17
b1001 !
b1001 (
1.
0-
13
0%
b10 $
b10 '
b10 E
#1715
14
1+
b1010 !
b1010 (
0.
1/
1%
#1725
00
11
b1010 !
b1010 (
0.
0/
1-
0%
b11 $
b11 '
b11 E
#1730
b1011 !
b1011 (
1.
1%
#1740
0+
14
05
0*
0:
0;
10
01
16
07
0<
1=
b1011 !
b1011 (
1.
0-
03
19
0%
b100 $
b100 '
b100 E
#1745
1:
1*
04
15
1+
b1100 !
b1100 (
0.
1/
1%
#1755
00
11
b1100 !
b1100 (
0.
0/
1-
0%
b101 $
b101 '
b101 E
#1760
b1101 !
b1101 (
1.
1%
#1770
0+
04
05
10
01
06
17
b1101 !
b1101 (
1.
0-
13
0%
b110 $
b110 '
b110 E
#1775
14
1+
b1110 !
b1110 (
0.
1/
1%
#1785
00
11
b1110 !
b1110 (
0.
0/
1-
0%
b111 $
b111 '
b111 E
#1790
b1111 !
b1111 (
1.
1%
#1800
0"
0+
14
05
0*
1:
0;
0)
1@
0A
10
01
16
07
1<
0=
1B
b1111 !
b1111 (
1.
0-
03
09
1?
0%
b1000 $
b1000 '
b1000 E
#1805
1"
0@
1A
1)
0:
1;
1*
04
15
1+
b0 !
b0 (
0.
1/
1%
#1815
00
11
b0 !
b0 (
0.
0/
1-
0%
b1001 $
b1001 '
b1001 E
#1820
b1 !
b1 (
1.
1%
#1830
0+
04
05
10
01
06
17
b1 !
b1 (
1.
0-
13
0%
b1010 $
b1010 '
b1010 E
#1835
14
1+
b10 !
b10 (
0.
1/
1%
#1845
00
11
b10 !
b10 (
0.
0/
1-
0%
b1011 $
b1011 '
b1011 E
#1850
b11 !
b11 (
1.
1%
#1860
0+
14
05
0*
0:
0;
10
01
16
07
0<
1=
b11 !
b11 (
1.
0-
03
19
0%
b1100 $
b1100 '
b1100 E
#1865
1:
1*
04
15
1+
b100 !
b100 (
0.
1/
1%
#1875
00
11
b100 !
b100 (
0.
0/
1-
0%
b1101 $
b1101 '
b1101 E
#1880
b101 !
b101 (
1.
1%
#1890
0+
04
05
10
01
06
17
b101 !
b101 (
1.
0-
13
0%
b1110 $
b1110 '
b1110 E
#1895
14
1+
b110 !
b110 (
0.
1/
1%
#1905
00
11
b110 !
b110 (
0.
0/
1-
0%
b1111 $
b1111 '
b1111 E
#1910
b111 !
b111 (
1.
1%
#1920
0"
04
0:
1@
0A
0+
0*
0)
01
07
0=
b1000 !
b1000 (
0.
0-
03
09
0?
0,
02
08
1>
0%
b0 $
b0 '
b1000 #
b1000 &
b1000 D
b0 E
#1925
b1001 !
b1001 (
1.
1%
#1935
10
b1001 !
b1001 (
1.
1-
0%
b1 $
b1 '
b1 E
#1940
14
1+
b1010 !
b1010 (
0.
1/
1%
#1950
0+
00
16
b1010 !
b1010 (
0.
0/
0-
13
0%
b10 $
b10 '
b10 E
#1955
b1011 !
b1011 (
1.
1%
#1965
10
b1011 !
b1011 (
1.
1-
0%
b11 $
b11 '
b11 E
#1970
1:
1*
04
15
1+
b1100 !
b1100 (
0.
1/
1%
#1980
0"
1@
0A
0*
0)
05
1:
0;
0+
00
06
1<
b1100 !
b1100 (
0.
0/
0-
03
19
0%
b100 $
b100 '
b100 E
#1985
b1101 !
b1101 (
1.
1%
#1995
10
b1101 !
b1101 (
1.
1-
0%
b101 $
b101 '
b101 E
#2000
14
1+
b1110 !
b1110 (
0.
1/
1%
#2010
0+
00
16
b1110 !
b1110 (
0.
0/
0-
13
0%
b110 $
b110 '
b110 E
#2015
b1111 !
b1111 (
1.
1%
#2025
10
b1111 !
b1111 (
1.
1-
0%
b111 $
b111 '
b111 E
#2030
1"
0@
1A
1)
0:
1;
1*
04
15
1+
b0 !
b0 (
0.
1/
1%
#2040
0*
0)
05
0:
0;
0@
0A
0+
00
06
0<
0B
1C
b0 !
b0 (
0.
0/
0-
03
09
1?
0%
b1000 $
b1000 '
b1000 E
#2045
b1 !
b1 (
1.
1%
#2055
10
b1 !
b1 (
1.
1-
0%
b1001 $
b1001 '
b1001 E
#2060
14
1+
b10 !
b10 (
0.
1/
1%
#2070
0+
00
16
b10 !
b10 (
0.
0/
0-
13
0%
b1010 $
b1010 '
b1010 E
#2075
b11 !
b11 (
1.
1%
#2085
10
b11 !
b11 (
1.
1-
0%
b1011 $
b1011 '
b1011 E
#2090
1:
1*
04
15
1+
b100 !
b100 (
0.
1/
1%
#2100
0@
0*
0)
05
1:
0;
0+
00
06
1<
b100 !
b100 (
0.
0/
0-
03
19
0%
b1100 $
b1100 '
b1100 E
#2105
b101 !
b101 (
1.
1%
#2115
10
b101 !
b101 (
1.
1-
0%
b1101 $
b1101 '
b1101 E
#2120
14
1+
b110 !
b110 (
0.
1/
1%
#2130
0+
00
16
b110 !
b110 (
0.
0/
0-
13
0%
b1110 $
b1110 '
b1110 E
#2135
b111 !
b111 (
1.
1%
#2145
10
b111 !
b111 (
1.
1-
0%
b1111 $
b1111 '
b1111 E
