SRAM/ram.sv
module ram #(
  parameter WIDTH = 4,
  parameter DEPTH = 32
)(
    input  logic                     clk,    // clock
    input  logic                     we,     // write enable
    input  logic                     cs,     // chip select
    input  logic                     oe,     // output enable
    input  logic [$clog2(DEPTH)-1:0] addr,   // log2(DEPTH)-bit address (DEPTH locations)
    input  logic [      WIDTH-1:0]   din,    // WIDTH-bit data input
    output logic [      WIDTH-1:0]   dout    // WIDTH-bit data output
);

  // Memory array, DEPTH locations, each WIDTH bits wide
  logic [WIDTH-1:0] mem[0:DEPTH-1];

  // Synchronous write
  always_ff @(posedge clk) begin : write
    if (cs && we)
      mem[addr] <= din;
  end

  // Synchronous read (For targeting FPGAs)
  always_ff @(posedge clk) begin : read
    if (cs && oe && !we)
      dout <= mem[addr];
    // else: keep revious value
  end

  // // Asynchronous read
  // always_comb begin
  //   if (cs && oe && !we)
  //     dout = mem[addr];
  //   else
  //     // dout = '0;   
  //     dout = 'z;  // tri-state for sim only 
  // end
endmodule

SRAM/mem_fsm.sv
module mem_fsm #(
    parameter WIDTH = 4,
    parameter DEPTH = 32
) (
    input  logic clk,
    input  logic rst,
    input  logic wr_req,  // write request flag
    input  logic re_req,  // read request flag
    output logic we,      // write enable control signal
    output logic cs,      // chip select control signal
    output logic oe       // output enable (read) control signal

);

  localparam IDLE = 2'b00;
  localparam WRITE = 2'b01;
  localparam READ = 2'b10;

  logic [1:0] state, next_state;

  always_ff @(posedge clk or posedge rst) begin : state_transition
    if (rst) begin
      state <= IDLE;
    end else begin
      state <= next_state;
    end
  end

  always_comb begin : state_logic
    case (state)
      IDLE: begin
        if (wr_req) next_state = WRITE;
        else if (re_req) next_state = READ;
        else next_state = IDLE;
      end
      WRITE: next_state = IDLE;
      READ: next_state = IDLE;
      default: next_state = IDLE;
    endcase
  end

  // output logic
  always_comb begin : output_logic
    cs = 0;
    we = 0;
    oe = 0;
    case (state)
      WRITE: begin
        cs = 1;
        we = 1;
      end
      READ: begin
        cs = 1;
        oe = 1;
      end
      default: ;
    endcase
  end
endmodule

SRAM/sram_top.sv
module sram_top #(
    parameter WIDTH = 4,
    parameter DEPTH = 32
) (
    input  logic                     clk,      // clock
    input  logic                     rst,      // reset
    input  logic                     wr_req,   // write request
    input  logic                     re_req,   // read request
    input  logic [$clog2(DEPTH)-1:0] addr_in,  // external address input
    input  logic [        WIDTH-1:0] din_in,   // external data input
    output logic [        WIDTH-1:0] dout_out  // ram data output
);

  // Internal registers
  logic cs, we, oe;

  // RAM Output
  logic [WIDTH-1:0] ram_dout;

  mem_fsm #(
      .WIDTH(WIDTH),
      .DEPTH(DEPTH)
  ) fsm (
      .clk   (clk),
      .rst   (rst),
      .wr_req(wr_req),
      .re_req(re_req),
      .we    (we),
      .cs    (cs),
      .oe    (oe)
  );

  ram #(
      .WIDTH(WIDTH),
      .DEPTH(DEPTH)
  ) ram_i (
      .clk (clk),
      .we  (we),
      .cs  (cs),
      .oe  (oe),
      .addr(addr_in),
      .din (din_in),
      .dout(ram_dout)
  );

  assign dout_out = ram_dout;
endmodule

SRAM/sram_top_tb.sv
module sram_top_tb;

  parameter WIDTH = 4;
  parameter DEPTH = 32;
  parameter ADDR_WIDTH = $clog2(DEPTH);

  logic                  clk;
  logic                  rst;
  logic                  wr_req;
  logic                  re_req;
  logic [ADDR_WIDTH-1:0] addr_in;
  logic [     WIDTH-1:0] din_in;
  logic [     WIDTH-1:0] dout_out;

  // DUT
  sram_top #(WIDTH, DEPTH) uut (
      .clk(clk),
      .rst(rst),
      .wr_req(wr_req),
      .re_req(re_req),
      .addr_in(addr_in),
      .din_in(din_in),
      .dout_out(dout_out)
  );

  initial begin
    $dumpfile("sram_top.vcd");
    $dumpvars(0, sram_top_tb);
  end

  always #5 clk = ~clk;

  initial begin
    clk = 0;
    rst = 1;
    wr_req = 0;
    re_req = 0;
    addr_in = 0;
    din_in = 4'b1010;

    #12;
    rst = 0;

    // Write din_in into all 32 addresses
    for (int i = 0; i < DEPTH; i++) begin
      addr_in = i;
      din_in  = 4'b1010;
      wr_req  = 1;
      #10;
      wr_req = 0;
      #10;
    end
  end

endmodule

SRAM/sram_top.vcd
$date
	Wed Jul  2 15:46:59 2025
$end
$version
	Icarus Verilog
$end
$timescale
	1s
$end
$scope module sram_top_tb $end
$var wire 4 ! dout_out [3:0] $end
$var parameter 32 " ADDR_WIDTH $end
$var parameter 32 # DEPTH $end
$var parameter 32 $ WIDTH $end
$var reg 5 % addr_in [4:0] $end
$var reg 1 & clk $end
$var reg 4 ' din_in [3:0] $end
$var reg 1 ( re_req $end
$var reg 1 ) rst $end
$var reg 1 * wr_req $end
$scope module uut $end
$var wire 5 + addr_in [4:0] $end
$var wire 1 & clk $end
$var wire 4 , din_in [3:0] $end
$var wire 4 - dout_out [3:0] $end
$var wire 1 ( re_req $end
$var wire 1 ) rst $end
$var wire 1 * wr_req $end
$var wire 1 . we $end
$var wire 4 / ram_dout [3:0] $end
$var wire 1 0 oe $end
$var wire 1 1 cs $end
$var parameter 32 2 DEPTH $end
$var parameter 32 3 WIDTH $end
$scope module fsm $end
$var wire 1 & clk $end
$var wire 1 ( re_req $end
$var wire 1 ) rst $end
$var wire 1 * wr_req $end
$var parameter 32 4 DEPTH $end
$var parameter 2 5 IDLE $end
$var parameter 2 6 READ $end
$var parameter 32 7 WIDTH $end
$var parameter 2 8 WRITE $end
$var reg 1 1 cs $end
$var reg 2 9 next_state [1:0] $end
$var reg 1 0 oe $end
$var reg 2 : state [1:0] $end
$var reg 1 . we $end
$scope begin output_logic $end
$upscope $end
$scope begin state_logic $end
$upscope $end
$scope begin state_transition $end
$upscope $end
$upscope $end
$scope module ram_i $end
$var wire 5 ; addr [4:0] $end
$var wire 1 & clk $end
$var wire 1 1 cs $end
$var wire 4 < din [3:0] $end
$var wire 1 0 oe $end
$var wire 1 . we $end
$var parameter 32 = DEPTH $end
$var parameter 32 > WIDTH $end
$var reg 4 ? dout [3:0] $end
$scope begin read $end
$upscope $end
$scope begin write $end
$upscope $end
$upscope $end
$upscope $end
$scope begin $ivl_for_loop0 $end
$var integer 32 @ i [31:0] $end
$upscope $end
$scope begin $ivl_for_loop1 $end
$var integer 32 A i [31:0] $end
$upscope $end
$upscope $end
$enddefinitions $end
$comment Show the parameter values. $end
$dumpall
b100 >
b100000 =
b1 8
b100 7
b10 6
b0 5
b100000 4
b100 3
b100000 2
b100 $
b100000 #
b101 "
$end
#0
$dumpvars
b0 A
b0 @
bx ?
b1010 <
b0 ;
b0 :
b0 9
01
00
bx /
0.
bx -
b1010 ,
b0 +
0*
1)
0(
b1010 '
0&
b0 %
bx !
$end
#5
1&
#10
0&
#12
b1 9
1*
0)
#15
1.
11
b0 9
b1 :
1&
#20
0&
#22
0*
#25
0.
01
b0 :
1&
#30
0&
#32
b1 9
1*
b1 %
b1 +
b1 ;
b1 @
#35
1.
11
b0 9
b1 :
1&
#40
0&
#42
0*
#45
0.
01
b0 :
1&
#50
0&
#52
b1 9
1*
b10 %
b10 +
b10 ;
b10 @
#55
1.
11
b0 9
b1 :
1&
#60
0&
#62
0*
#65
0.
01
b0 :
1&
#70
0&
#72
b1 9
1*
b11 %
b11 +
b11 ;
b11 @
#75
1.
11
b0 9
b1 :
1&
#80
0&
#82
0*
#85
0.
01
b0 :
1&
#90
0&
#92
b1 9
1*
b100 %
b100 +
b100 ;
b100 @
#95
1.
11
b0 9
b1 :
1&
#100
0&
#102
0*
#105
0.
01
b0 :
1&
#110
0&
#112
b1 9
1*
b101 %
b101 +
b101 ;
b101 @
#115
1.
11
b0 9
b1 :
1&
#120
0&
#122
0*
#125
0.
01
b0 :
1&
#130
0&
#132
b1 9
1*
b110 %
b110 +
b110 ;
b110 @
#135
1.
11
b0 9
b1 :
1&
#140
0&
#142
0*
#145
0.
01
b0 :
1&
#150
0&
#152
b1 9
1*
b111 %
b111 +
b111 ;
b111 @
#155
1.
11
b0 9
b1 :
1&
#160
0&
#162
0*
#165
0.
01
b0 :
1&
#170
0&
#172
b1 9
1*
b1000 %
b1000 +
b1000 ;
b1000 @
#175
1.
11
b0 9
b1 :
1&
#180
0&
#182
0*
#185
0.
01
b0 :
1&
#190
0&
#192
b1 9
1*
b1001 %
b1001 +
b1001 ;
b1001 @
#195
1.
11
b0 9
b1 :
1&
#200
0&
#202
0*
#205
0.
01
b0 :
1&
#210
0&
#212
b1 9
1*
b1010 %
b1010 +
b1010 ;
b1010 @
#215
1.
11
b0 9
b1 :
1&
#220
0&
#222
0*
#225
0.
01
b0 :
1&
#230
0&
#232
b1 9
1*
b1011 %
b1011 +
b1011 ;
b1011 @
#235
1.
11
b0 9
b1 :
1&
#240
0&
#242
0*
#245
0.
01
b0 :
1&
#250
0&
#252
b1 9
1*
b1100 %
b1100 +
b1100 ;
b1100 @
#255
1.
11
b0 9
b1 :
1&
#260
0&
#262
0*
#265
0.
01
b0 :
1&
#270
0&
#272
b1 9
1*
b1101 %
b1101 +
b1101 ;
b1101 @
#275
1.
11
b0 9
b1 :
1&
#280
0&
#282
0*
#285
0.
01
b0 :
1&
#290
0&
#292
b1 9
1*
b1110 %
b1110 +
b1110 ;
b1110 @
#295
1.
11
b0 9
b1 :
1&
#300
0&
#302
0*
#305
0.
01
b0 :
1&
#310
0&
#312
b1 9
1*
b1111 %
b1111 +
b1111 ;
b1111 @
#315
1.
11
b0 9
b1 :
1&
#320
0&
#322
0*
#325
0.
01
b0 :
1&
#330
0&
#332
b1 9
1*
b10000 %
b10000 +
b10000 ;
b10000 @
#335
1.
11
b0 9
b1 :
1&
#340
0&
#342
0*
#345
0.
01
b0 :
1&
#350
0&
#352
b1 9
1*
b10001 %
b10001 +
b10001 ;
b10001 @
#355
1.
11
b0 9
b1 :
1&
#360
0&
#362
0*
#365
0.
01
b0 :
1&
#370
0&
#372
b1 9
1*
b10010 %
b10010 +
b10010 ;
b10010 @
#375
1.
11
b0 9
b1 :
1&
#380
0&
#382
0*
#385
0.
01
b0 :
1&
#390
0&
#392
b1 9
1*
b10011 %
b10011 +
b10011 ;
b10011 @
#395
1.
11
b0 9
b1 :
1&
#400
0&
#402
0*
#405
0.
01
b0 :
1&
#410
0&
#412
b1 9
1*
b10100 %
b10100 +
b10100 ;
b10100 @
#415
1.
11
b0 9
b1 :
1&
#420
0&
#422
0*
#425
0.
01
b0 :
1&
#430
0&
#432
b1 9
1*
b10101 %
b10101 +
b10101 ;
b10101 @
#435
1.
11
b0 9
b1 :
1&
#440
0&
#442
0*
#445
0.
01
b0 :
1&
#450
0&
#452
b1 9
1*
b10110 %
b10110 +
b10110 ;
b10110 @
#455
1.
11
b0 9
b1 :
1&
#460
0&
#462
0*
#465
0.
01
b0 :
1&
#470
0&
#472
b1 9
1*
b10111 %
b10111 +
b10111 ;
b10111 @
#475
1.
11
b0 9
b1 :
1&
#480
0&
#482
0*
#485
0.
01
b0 :
1&
#490
0&
#492
b1 9
1*
b11000 %
b11000 +
b11000 ;
b11000 @
#495
1.
11
b0 9
b1 :
1&
#500
0&
#502
0*
#505
0.
01
b0 :
1&
#510
0&
#512
b1 9
1*
b11001 %
b11001 +
b11001 ;
b11001 @
#515
1.
11
b0 9
b1 :
1&
#520
0&
#522
0*
#525
0.
01
b0 :
1&
#530
0&
#532
b1 9
1*
b11010 %
b11010 +
b11010 ;
b11010 @
#535
1.
11
b0 9
b1 :
1&
#540
0&
#542
0*
#545
0.
01
b0 :
1&
#550
0&
#552
b1 9
1*
b11011 %
b11011 +
b11011 ;
b11011 @
#555
1.
11
b0 9
b1 :
1&
#560
0&
#562
0*
#565
0.
01
b0 :
1&
#570
0&
#572
b1 9
1*
b11100 %
b11100 +
b11100 ;
b11100 @
#575
1.
11
b0 9
b1 :
1&
#580
0&
#582
0*
#585
0.
01
b0 :
1&
#590
0&
#592
b1 9
1*
b11101 %
b11101 +
b11101 ;
b11101 @
#595
1.
11
b0 9
b1 :
1&
#600
0&
#602
0*
#605
0.
01
b0 :
1&
#610
0&
#612
b1 9
1*
b11110 %
b11110 +
b11110 ;
b11110 @
#615
1.
11
b0 9
b1 :
1&
#620
0&
#622
0*
#625
0.
01
b0 :
1&
#630
0&
#632
b1 9
1*
b11111 %
b11111 +
b11111 ;
b11111 @
#635
1.
11
b0 9
b1 :
1&
#640
0&
#642
0*
#645
0.
01
b0 :
1&
#650
0&
#652
b10 9
1(
b0 %
b0 +
b0 ;
b100000 @
#655
10
11
b0 9
b10 :
1&
#660
0&
#662
0(
#665
00
01
b0 :
b1010 !
b1010 -
b1010 /
b1010 ?
1&
#670
0&
#672
b10 9
1(
b1 %
b1 +
b1 ;
b1 A
#675
10
11
b0 9
b10 :
1&
#680
0&
#682
0(
#685
00
01
b0 :
1&
#690
0&
#692
b10 9
1(
b10 %
b10 +
b10 ;
b10 A
#695
10
11
b0 9
b10 :
1&
#700
0&
#702
0(
#705
00
01
b0 :
1&
#710
0&
#712
b10 9
1(
b11 %
b11 +
b11 ;
b11 A
#715
10
11
b0 9
b10 :
1&
#720
0&
#722
0(
#725
00
01
b0 :
1&
#730
0&
#732
b10 9
1(
b100 %
b100 +
b100 ;
b100 A
#735
10
11
b0 9
b10 :
1&
#740
0&
#742
0(
#745
00
01
b0 :
1&
#750
0&
#752
b10 9
1(
b101 %
b101 +
b101 ;
b101 A
#755
10
11
b0 9
b10 :
1&
#760
0&
#762
0(
#765
00
01
b0 :
1&
#770
0&
#772
b10 9
1(
b110 %
b110 +
b110 ;
b110 A
#775
10
11
b0 9
b10 :
1&
#780
0&
#782
0(
#785
00
01
b0 :
1&
#790
0&
#792
b10 9
1(
b111 %
b111 +
b111 ;
b111 A
#795
10
11
b0 9
b10 :
1&
#800
0&
#802
0(
#805
00
01
b0 :
1&
#810
0&
#812
b10 9
1(
b1000 %
b1000 +
b1000 ;
b1000 A
#815
10
11
b0 9
b10 :
1&
#820
0&
#822
0(
#825
00
01
b0 :
1&
#830
0&
#832
b10 9
1(
b1001 %
b1001 +
b1001 ;
b1001 A
#835
10
11
b0 9
b10 :
1&
#840
0&
#842
0(
#845
00
01
b0 :
1&
#850
0&
#852
b10 9
1(
b1010 %
b1010 +
b1010 ;
b1010 A
#855
10
11
b0 9
b10 :
1&
#860
0&
#862
0(
#865
00
01
b0 :
1&
#870
0&
#872
b10 9
1(
b1011 %
b1011 +
b1011 ;
b1011 A
#875
10
11
b0 9
b10 :
1&
#880
0&
#882
0(
#885
00
01
b0 :
1&
#890
0&
#892
b10 9
1(
b1100 %
b1100 +
b1100 ;
b1100 A
#895
10
11
b0 9
b10 :
1&
#900
0&
#902
0(
#905
00
01
b0 :
1&
#910
0&
#912
b10 9
1(
b1101 %
b1101 +
b1101 ;
b1101 A
#915
10
11
b0 9
b10 :
1&
#920
0&
#922
0(
#925
00
01
b0 :
1&
#930
0&
#932
b10 9
1(
b1110 %
b1110 +
b1110 ;
b1110 A
#935
10
11
b0 9
b10 :
1&
#940
0&
#942
0(
#945
00
01
b0 :
1&
#950
0&
#952
b10 9
1(
b1111 %
b1111 +
b1111 ;
b1111 A
#955
10
11
b0 9
b10 :
1&
#960
0&
#962
0(
#965
00
01
b0 :
1&
#970
0&
#972
b10 9
1(
b10000 %
b10000 +
b10000 ;
b10000 A
#975
10
11
b0 9
b10 :
1&
#980
0&
#982
0(
#985
00
01
b0 :
1&
#990
0&
#992
b10 9
1(
b10001 %
b10001 +
b10001 ;
b10001 A
#995
10
11
b0 9
b10 :
1&
#1000
0&
#1002
0(
#1005
00
01
b0 :
1&
#1010
0&
#1012
b10 9
1(
b10010 %
b10010 +
b10010 ;
b10010 A
#1015
10
11
b0 9
b10 :
1&
#1020
0&
#1022
0(
#1025
00
01
b0 :
1&
#1030
0&
#1032
b10 9
1(
b10011 %
b10011 +
b10011 ;
b10011 A
#1035
10
11
b0 9
b10 :
1&
#1040
0&
#1042
0(
#1045
00
01
b0 :
1&
#1050
0&
#1052
b10 9
1(
b10100 %
b10100 +
b10100 ;
b10100 A
#1055
10
11
b0 9
b10 :
1&
#1060
0&
#1062
0(
#1065
00
01
b0 :
1&
#1070
0&
#1072
b10 9
1(
b10101 %
b10101 +
b10101 ;
b10101 A
#1075
10
11
b0 9
b10 :
1&
#1080
0&
#1082
0(
#1085
00
01
b0 :
1&
#1090
0&
#1092
b10 9
1(
b10110 %
b10110 +
b10110 ;
b10110 A
#1095
10
11
b0 9
b10 :
1&
#1100
0&
#1102
0(
#1105
00
01
b0 :
1&
#1110
0&
#1112
b10 9
1(
b10111 %
b10111 +
b10111 ;
b10111 A
#1115
10
11
b0 9
b10 :
1&
#1120
0&
#1122
0(
#1125
00
01
b0 :
1&
#1130
0&
#1132
b10 9
1(
b11000 %
b11000 +
b11000 ;
b11000 A
#1135
10
11
b0 9
b10 :
1&
#1140
0&
#1142
0(
#1145
00
01
b0 :
1&
#1150
0&
#1152
b10 9
1(
b11001 %
b11001 +
b11001 ;
b11001 A
#1155
10
11
b0 9
b10 :
1&
#1160
0&
#1162
0(
#1165
00
01
b0 :
1&
#1170
0&
#1172
b10 9
1(
b11010 %
b11010 +
b11010 ;
b11010 A
#1175
10
11
b0 9
b10 :
1&
#1180
0&
#1182
0(
#1185
00
01
b0 :
1&
#1190
0&
#1192
b10 9
1(
b11011 %
b11011 +
b11011 ;
b11011 A
#1195
10
11
b0 9
b10 :
1&
#1200
0&
#1202
0(
#1205
00
01
b0 :
1&
#1210
0&
#1212
b10 9
1(
b11100 %
b11100 +
b11100 ;
b11100 A
#1215
10
11
b0 9
b10 :
1&
#1220
0&
#1222
0(
#1225
00
01
b0 :
1&
#1230
0&
#1232
b10 9
1(
b11101 %
b11101 +
b11101 ;
b11101 A
#1235
10
11
b0 9
b10 :
1&
#1240
0&
#1242
0(
#1245
00
01
b0 :
1&
#1250
0&
#1252
b10 9
1(
b11110 %
b11110 +
b11110 ;
b11110 A
#1255
10
11
b0 9
b10 :
1&
#1260
0&
#1262
0(
#1265
00
01
b0 :
1&
#1270
0&
#1272
b10 9
1(
b11111 %
b11111 +
b11111 ;
b11111 A
#1275
10
11
b0 9
b10 :
1&
#1280
0&
#1282
0(
#1285
00
01
b0 :
1&
#1290
0&
#1292
b100000 A
