2_speed_BCD_cnt/bcd4.sv
module bcd4 (
    input  logic       clk,
    input  logic       rst,
    output logic [3:0] out
);
  logic [3:0] cnt;

  always_ff @(posedge clk or posedge rst) begin : bcd
    if (rst) begin
      cnt <= '0;
    end else if (cnt == 4'h9) begin
      cnt <= '0;
    end else begin
      cnt <= cnt + 1;
    end
  end

  assign out = cnt;
endmodule

8_bit_CSA/mux2.sv
module mux2 (
    input  logic [1:0] d,
    input  logic       s,
    output logic       y
);

  assign y = s ? d[1] : d[0];

  // always_comb begin : mux
  //   if (s) begin
  //     y = d[1];
  //   end else begin
  //     y = d[0];
  //   end
  // end
endmodule

2_speed_BCD_cnt/clkdiv4.sv
module clkdiv4 (
    input  logic clk1,
    input  logic rst,
    output logic clk2
);
  logic [1:0] cnt;

  always_ff @(posedge clk1 or posedge rst) begin : clk_div
    if (rst) begin
      cnt  <= '0;
      clk2 <= 0;
    end else begin
      cnt <= cnt + 1;
      if (cnt == 3) begin
        clk2 <= ~clk2;
      end
    end
  end
endmodule

2_speed_BCD_cnt/BCD_2_speed.sv
`include "../8_bit_CSA/mux2.sv"
`include "../2_speed_BCD_cnt/bcd4.sv"
`include "../2_speed_BCD_cnt/clkdiv4.sv"

module BCD_2_speed (
    input  logic       clk,
    input  logic       rst,
    input  logic       sel,
    output logic [3:0] y
);

  // Internal Registers
  logic clk_div_4;
  logic clk_y;

  clkdiv4 g1 (
      .clk1(clk),
      .rst (rst),
      .clk2(clk_div_4)
  );

  mux2 g2 (
      .d({clk_div_4, clk}),
      .s(sel),
      .y(clk_y)
  );

  bcd4 g3 (
      .clk(clk_y),
      .rst(rst),
      .out(y)
  );
endmodule

2_speed_BCD_cnt/BCD_2_speed_tb.sv
module BCD_2_speed_tb;
  logic       clk;
  logic       rst;
  logic       sel;
  logic [3:0] y;

  BCD_2_speed uut (
      .clk(clk),
      .rst(rst),
      .sel(sel),
      .y  (y)
  );

  // VCD dump
  initial begin
    $dumpfile("BCD_2_speed.vcd");
    $dumpvars(0, BCD_2_speed_tb);
  end

  initial begin
    clk = 0;
    sel = 0;
    rst = 1;
    #10;
    rst = 0;
    repeat (200) begin
      clk = ~clk;
      sel = $urandom_range(0, 1);
      #5;
    end
    $finish;
  end
endmodule

2_speed_BCD_cnt/BCD_2_speed.vcd
$date
	Mon Jun  9 15:59:02 2025
$end
$version
	Icarus Verilog
$end
$timescale
	1s
$end
$scope module BCD_2_speed_tb $end
$var wire 4 ! y [3:0] $end
$var reg 1 " clk $end
$var reg 1 # rst $end
$var reg 1 $ sel $end
$scope module uut $end
$var wire 1 " clk $end
$var wire 1 # rst $end
$var wire 1 $ sel $end
$var wire 4 % y [3:0] $end
$var wire 1 & clk_y $end
$var wire 1 ' clk_div_4 $end
$scope module g1 $end
$var wire 1 " clk1 $end
$var wire 1 # rst $end
$var reg 1 ' clk2 $end
$var reg 2 ( cnt [1:0] $end
$scope begin clk_div $end
$upscope $end
$upscope $end
$scope module g2 $end
$var wire 2 ) d [1:0] $end
$var wire 1 $ s $end
$var wire 1 & y $end
$upscope $end
$scope module g3 $end
$var wire 1 & clk $end
$var wire 4 * out [3:0] $end
$var wire 1 # rst $end
$var reg 4 + cnt [3:0] $end
$scope begin bcd $end
$upscope $end
$upscope $end
$upscope $end
$upscope $end
$enddefinitions $end
$comment Show the parameter values. $end
$dumpall
$end
#0
$dumpvars
b0 +
b0 *
b0 )
b0 (
0'
0&
b0 %
0$
1#
0"
b0 !
$end
#10
b1 (
1$
b1 )
1"
0#
#15
0$
b0 )
0"
#20
b1 !
b1 %
b1 *
b1 +
b10 (
1&
b1 )
1"
#25
0&
b0 )
0"
#30
b11 (
1$
b1 )
1"
#35
b0 )
0"
#40
b10 !
b10 %
b10 *
b10 +
1'
b0 (
1&
0$
b11 )
1"
#45
0&
b10 )
0"
#50
b11 !
b11 %
b11 *
b11 +
b1 (
1&
1$
b11 )
1"
#55
b10 )
0"
#60
b10 (
b11 )
1"
#65
b10 )
0"
#70
b11 (
b11 )
1"
#75
b10 )
0"
#80
0&
0'
b0 (
b1 )
1"
#85
0$
b0 )
0"
#90
b100 !
b100 %
b100 *
b100 +
b1 (
1&
b1 )
1"
#95
0&
b0 )
0"
#100
b10 (
1$
b1 )
1"
#105
0$
b0 )
0"
#110
b101 !
b101 %
b101 *
b101 +
b11 (
1&
b1 )
1"
#115
0&
1$
b0 )
0"
#120
b110 !
b110 %
b110 *
b110 +
1&
1'
b0 (
b11 )
1"
#125
0&
0$
b10 )
0"
#130
b111 !
b111 %
b111 *
b111 +
b1 (
1&
b11 )
1"
#135
0&
b10 )
0"
#140
b1000 !
b1000 %
b1000 *
b1000 +
b10 (
1&
1$
b11 )
1"
#145
0&
0$
b10 )
0"
#150
b1001 !
b1001 %
b1001 *
b1001 +
b11 (
1&
b11 )
1"
#155
0&
b10 )
0"
#160
b0 !
b0 %
b0 *
b0 +
0'
b0 (
1&
b1 )
1"
#165
0&
1$
b0 )
0"
#170
b1 !
b1 %
b1 *
b1 +
b1 (
1&
0$
b1 )
1"
#175
0&
1$
b0 )
0"
#180
b10 (
b1 )
1"
#185
0$
b0 )
0"
#190
b10 !
b10 %
b10 *
b10 +
b11 (
1&
b1 )
1"
#195
0&
b0 )
0"
#200
b11 !
b11 %
b11 *
b11 +
1'
b0 (
1&
b11 )
1"
#205
0&
b10 )
0"
#210
b100 !
b100 %
b100 *
b100 +
b1 (
1&
1$
b11 )
1"
#215
0&
0$
b10 )
0"
#220
b101 !
b101 %
b101 *
b101 +
b10 (
1&
b11 )
1"
#225
0&
b10 )
0"
#230
b110 !
b110 %
b110 *
b110 +
b11 (
1&
1$
b11 )
1"
#235
0&
0$
b10 )
0"
#240
b111 !
b111 %
b111 *
b111 +
0'
b0 (
0&
1$
b1 )
1"
#245
b0 )
0"
#250
b1000 !
b1000 %
b1000 *
b1000 +
b1 (
1&
0$
b1 )
1"
#255
0&
b0 )
0"
#260
b10 (
1$
b1 )
1"
#265
b0 )
0"
#270
b11 (
b1 )
1"
#275
0$
b0 )
0"
#280
b1001 !
b1001 %
b1001 *
b1001 +
1&
1'
b0 (
1$
b11 )
1"
#285
0&
0$
b10 )
0"
#290
b0 !
b0 %
b0 *
b0 +
b1 (
1&
1$
b11 )
1"
#295
b10 )
0"
#300
b10 (
b11 )
1"
#305
b10 )
0"
#310
b11 (
0$
b11 )
1"
#315
1$
b10 )
0"
#320
0'
b0 (
0$
b1 )
1"
#325
0&
b0 )
0"
#330
b1 (
1$
b1 )
1"
#335
b0 )
0"
#340
b1 !
b1 %
b1 *
b1 +
b10 (
1&
0$
b1 )
1"
#345
0&
1$
b0 )
0"
#350
b10 !
b10 %
b10 *
b10 +
b11 (
1&
0$
b1 )
1"
#355
0&
1$
b0 )
0"
#360
b11 !
b11 %
b11 *
b11 +
1&
1'
b0 (
b11 )
1"
#365
b10 )
0"
#370
b1 (
b11 )
1"
#375
b10 )
0"
#380
b10 (
b11 )
1"
#385
b10 )
0"
#390
b11 (
b11 )
1"
#395
0&
0$
b10 )
0"
#400
b100 !
b100 %
b100 *
b100 +
0'
b0 (
1&
b1 )
1"
#405
0&
b0 )
0"
#410
b101 !
b101 %
b101 *
b101 +
b1 (
1&
b1 )
1"
#415
0&
1$
b0 )
0"
#420
b110 !
b110 %
b110 *
b110 +
b10 (
1&
0$
b1 )
1"
#425
0&
b0 )
0"
#430
b111 !
b111 %
b111 *
b111 +
b11 (
1&
b1 )
1"
#435
0&
b0 )
0"
#440
b1000 !
b1000 %
b1000 *
b1000 +
1&
1'
b0 (
1$
b11 )
1"
#445
b10 )
0"
#450
b1 (
0$
b11 )
1"
#455
1$
b10 )
0"
#460
b10 (
0$
b11 )
1"
#465
1$
b10 )
0"
#470
b11 (
b11 )
1"
#475
0&
0$
b10 )
0"
#480
b1001 !
b1001 %
b1001 *
b1001 +
0'
b0 (
0&
1$
b1 )
1"
#485
b0 )
0"
#490
b1 (
b1 )
1"
#495
0$
b0 )
0"
#500
b10 (
1$
b1 )
1"
#505
0$
b0 )
0"
#510
b11 (
1$
b1 )
1"
#515
b0 )
0"
#520
b0 !
b0 %
b0 *
b0 +
1'
b0 (
1&
0$
b11 )
1"
#525
1$
b10 )
0"
#530
b1 (
b11 )
1"
#535
0&
0$
b10 )
0"
#540
b1 !
b1 %
b1 *
b1 +
b10 (
1&
b11 )
1"
#545
0&
b10 )
0"
#550
b10 !
b10 %
b10 *
b10 +
b11 (
1&
1$
b11 )
1"
#555
0&
0$
b10 )
0"
#560
b11 !
b11 %
b11 *
b11 +
0'
b0 (
0&
1$
b1 )
1"
#565
0$
b0 )
0"
#570
b100 !
b100 %
b100 *
b100 +
b1 (
1&
b1 )
1"
#575
0&
b0 )
0"
#580
b101 !
b101 %
b101 *
b101 +
b10 (
1&
b1 )
1"
#585
0&
1$
b0 )
0"
#590
b11 (
b1 )
1"
#595
0$
b0 )
0"
#600
b110 !
b110 %
b110 *
b110 +
1'
b0 (
1&
b11 )
1"
#605
1$
b10 )
0"
#610
b1 (
b11 )
1"
#615
0&
0$
b10 )
0"
#620
b111 !
b111 %
b111 *
b111 +
b10 (
1&
b11 )
1"
#625
0&
b10 )
0"
#630
b1000 !
b1000 %
b1000 *
b1000 +
b11 (
1&
b11 )
1"
#635
0&
b10 )
0"
#640
b1001 !
b1001 %
b1001 *
b1001 +
0'
b0 (
0&
1$
b1 )
1"
#645
b0 )
0"
#650
b0 !
b0 %
b0 *
b0 +
b1 (
1&
0$
b1 )
1"
#655
0&
1$
b0 )
0"
#660
b10 (
b1 )
1"
#665
b0 )
0"
#670
b11 (
b1 )
1"
#675
0$
b0 )
0"
#680
b1 !
b1 %
b1 *
b1 +
1'
b0 (
1&
b11 )
1"
#685
0&
b10 )
0"
#690
b10 !
b10 %
b10 *
b10 +
b1 (
1&
1$
b11 )
1"
#695
b10 )
0"
#700
b10 (
0$
b11 )
1"
#705
0&
b10 )
0"
#710
b11 !
b11 %
b11 *
b11 +
b11 (
1&
1$
b11 )
1"
#715
0&
0$
b10 )
0"
#720
b100 !
b100 %
b100 *
b100 +
0'
b0 (
0&
1$
b1 )
1"
#725
0$
b0 )
0"
#730
b1 (
1$
b1 )
1"
#735
b0 )
0"
#740
b101 !
b101 %
b101 *
b101 +
b10 (
1&
0$
b1 )
1"
#745
0&
b0 )
0"
#750
b11 (
1$
b1 )
1"
#755
0$
b0 )
0"
#760
b110 !
b110 %
b110 *
b110 +
1&
1'
b0 (
1$
b11 )
1"
#765
0&
0$
b10 )
0"
#770
b111 !
b111 %
b111 *
b111 +
b1 (
1&
b11 )
1"
#775
1$
b10 )
0"
#780
b10 (
b11 )
1"
#785
b10 )
0"
#790
b11 (
0$
b11 )
1"
#795
1$
b10 )
0"
#800
0&
0'
b0 (
b1 )
1"
#805
b0 )
0"
#810
b1000 !
b1000 %
b1000 *
b1000 +
b1 (
1&
0$
b1 )
1"
#815
0&
1$
b0 )
0"
#820
b10 (
b1 )
1"
#825
0$
b0 )
0"
#830
b1001 !
b1001 %
b1001 *
b1001 +
b11 (
1&
b1 )
1"
#835
0&
b0 )
0"
#840
b0 !
b0 %
b0 *
b0 +
1'
b0 (
1&
b11 )
1"
#845
1$
b10 )
0"
#850
b1 (
0$
b11 )
1"
#855
1$
b10 )
0"
#860
b10 (
0$
b11 )
1"
#865
1$
b10 )
0"
#870
b11 (
0$
b11 )
1"
#875
0&
b10 )
0"
#880
b1 !
b1 %
b1 *
b1 +
0'
b0 (
0&
1$
b1 )
1"
#885
0$
b0 )
0"
#890
b10 !
b10 %
b10 *
b10 +
b1 (
1&
b1 )
1"
#895
0&
1$
b0 )
0"
#900
b10 (
b1 )
1"
#905
b0 )
0"
#910
b11 (
b1 )
1"
#915
0$
b0 )
0"
#920
b11 !
b11 %
b11 *
b11 +
1'
b0 (
1&
b11 )
1"
#925
1$
b10 )
0"
#930
b1 (
b11 )
1"
#935
b10 )
0"
#940
b10 (
b11 )
1"
#945
0&
0$
b10 )
0"
#950
b100 !
b100 %
b100 *
b100 +
b11 (
1&
1$
b11 )
1"
#955
b10 )
0"
#960
0&
0'
b0 (
b1 )
1"
#965
b0 )
0"
#970
b1 (
b1 )
1"
#975
0$
b0 )
0"
#980
b101 !
b101 %
b101 *
b101 +
b10 (
1&
b1 )
1"
#985
0&
1$
b0 )
0"
#990
b110 !
b110 %
b110 *
b110 +
b11 (
1&
0$
b1 )
1"
#995
0&
b0 )
0"
#1000
b111 !
b111 %
b111 *
b111 +
1&
1'
b0 (
1$
b11 )
1"
#1005
0&
0$
b10 )
0"
