Stopwatch/watch.sv
module watch (
    input  logic       clk,
    input  logic       rst,
    input  logic       en,
    output logic [3:0] y2,
    output logic [3:0] y1,
    output logic [3:0] y0
);

  logic [3:0] cnt2;
  logic [3:0] cnt1;
  logic [3:0] cnt0;

  always_ff @(posedge clk or posedge rst) begin : counter
    if (rst) begin
      cnt0 <= '0;  // Ones
      cnt1 <= '0;  // Tens
      cnt2 <= '0;  // Hundreds
    end else if (en) begin
      if (cnt0 != 9) cnt0 <= cnt0 + 1;
      else if (cnt0 == 9 && cnt1 != 9) begin
        cnt1 <= cnt1 + 1;
        cnt0 <= 0;
      end else if (cnt0 == 9 && cnt1 == 9 && cnt2 != 9) begin
        cnt2 <= cnt2 + 1;
        cnt1 <= 0;
        cnt0 <= 0;
      end else begin
        cnt0 <= '0;
        cnt1 <= '0;
        cnt2 <= '0;
      end
    end
  end

  assign y2 = cnt2;
  assign y1 = cnt1;
  assign y0 = cnt0;
endmodule

Stopwatch/fsm.sv
// NOTE: FSM controls the start stop states of stopwatch
module fsm (
    input  logic clk,
    input  logic rst,
    input  logic start,
    input  logic stop,
    output logic en
);
  localparam IDLE = 2'b00;
  localparam RUN = 2'b01;
  localparam PAUSE = 2'b10;

  logic [1:0] state, next_state;

  always_ff @(posedge clk or posedge rst) begin : state_transition
    if (rst) begin
      state <= IDLE;
    end else begin
      state <= next_state;
    end
  end

  always_comb begin
    case (state)
      IDLE: begin
        if (start && ~stop) next_state = RUN;
        else next_state = IDLE;
      end

      RUN: begin
        if (stop && ~start) next_state = PAUSE;
        else next_state = RUN;
      end

      PAUSE: begin
        if (start && ~stop) next_state = RUN;
        else next_state = PAUSE;
      end

      default: next_state = IDLE;
    endcase
  end

  // Output logic
  assign en = (state == RUN);
endmodule

Stopwatch/clkdiv4.sv
module clkdiv4 (
    input  logic clk,
    input  logic rst,
    output logic clk2
);
  logic [1:0] cnt = '0;

  always_ff @(posedge clk or posedge rst) begin : clock_divider
    if (rst) begin
      clk2 <= 0;
      cnt  <= 0;
    end else begin
      cnt <= cnt + 1;
      if (cnt == 3) begin
        clk2 <= ~clk2;
      end
    end
  end
endmodule

Stopwatch/stopwatch_top.sv
`include "../Stopwatch/clkdiv4.sv"
`include "../Stopwatch/fsm.sv"
`include "../Stopwatch/watch.sv"

module stopwatch_top (
    input  logic       clk,
    input  logic       rst,
    input  logic       start,
    input  logic       stop,
    output logic [3:0] y2,
    output logic [3:0] y1,
    output logic [3:0] y0

);
  // Internal Registers
  logic clk2;
  logic en;

  // Module Instantiation
  clkdiv4 g1 (
      .clk (clk),
      .rst (rst),
      .clk2(clk2)
  );

  fsm g2 (
      .clk(clk2),
      .rst(rst),
      .start(start),
      .stop(stop),
      .en(en)
  );

  watch g3 (
      .clk(clk2),
      .rst(rst),
      .en (en),
      .y2 (y2),
      .y1 (y1),
      .y0 (y0)
  );

endmodule

Stopwatch/stopwatch_top_tb.sv
module stopwatch_top_tb;
  logic       clk;
  logic       rst;
  logic       start;
  logic       stop;
  logic [3:0] y2;
  logic [3:0] y1;
  logic [3:0] y0;

  stopwatch_top uut (
      .clk(clk),
      .rst(rst),
      .start(start),
      .stop(stop),
      .y2(y2),
      .y1(y1),
      .y0(y0)
  );

  initial begin
    $dumpfile("stopwatch_top.vcd");
    $dumpvars(0, stopwatch_top_tb);
  end

  always #1 clk = ~clk;

  initial begin
    rst   = 1;
    clk   = 0;
    start = 0;
    stop  = 0;
    #2;
    rst   = 0;
    start = 1;
    #800;
    start = 0;
    stop  = 1;
    #200;
    start = 1;
    stop  = 0;
    #200;
    rst   = 1;
    start = 0;
    #10;
    rst   = 0;
    start = 1;
    #20000;
    $finish;
  end








endmodule

Stopwatch/stopwatch_top.vcd
$date
	Mon Jun 30 17:01:04 2025
$end
$version
	Icarus Verilog
$end
$timescale
	1s
$end
$scope module stopwatch_top_tb $end
$var wire 4 ! y2 [3:0] $end
$var wire 4 " y1 [3:0] $end
$var wire 4 # y0 [3:0] $end
$var reg 1 $ clk $end
$var reg 1 % rst $end
$var reg 1 & start $end
$var reg 1 ' stop $end
$scope module uut $end
$var wire 1 $ clk $end
$var wire 1 % rst $end
$var wire 1 & start $end
$var wire 1 ' stop $end
$var wire 4 ( y2 [3:0] $end
$var wire 4 ) y1 [3:0] $end
$var wire 4 * y0 [3:0] $end
$var wire 1 + en $end
$var wire 1 , clk2 $end
$scope module g1 $end
$var wire 1 $ clk $end
$var wire 1 % rst $end
$var reg 1 , clk2 $end
$var reg 2 - cnt [1:0] $end
$scope begin clock_divider $end
$upscope $end
$upscope $end
$scope module g2 $end
$var wire 1 , clk $end
$var wire 1 % rst $end
$var wire 1 & start $end
$var wire 1 ' stop $end
$var wire 1 + en $end
$var parameter 2 . IDLE $end
$var parameter 2 / PAUSE $end
$var parameter 2 0 RUN $end
$var reg 2 1 next_state [1:0] $end
$var reg 2 2 state [1:0] $end
$scope begin state_transition $end
$upscope $end
$upscope $end
$scope module g3 $end
$var wire 1 , clk $end
$var wire 1 + en $end
$var wire 1 % rst $end
$var wire 4 3 y0 [3:0] $end
$var wire 4 4 y1 [3:0] $end
$var wire 4 5 y2 [3:0] $end
$var reg 4 6 cnt0 [3:0] $end
$var reg 4 7 cnt1 [3:0] $end
$var reg 4 8 cnt2 [3:0] $end
$scope begin counter $end
$upscope $end
$upscope $end
$upscope $end
$upscope $end
$enddefinitions $end
$comment Show the parameter values. $end
$dumpall
b1 0
b10 /
b0 .
$end
#0
$dumpvars
b0 8
b0 7
b0 6
b0 5
b0 4
b0 3
b0 2
b0 1
b0 -
0,
0+
b0 *
b0 )
b0 (
0'
0&
1%
0$
b0 #
b0 "
b0 !
$end
#1
1$
#2
b1 1
0$
1&
0%
#3
b1 -
1$
#4
0$
#5
b10 -
1$
#6
0$
#7
b11 -
1$
#8
0$
#9
1+
b1 2
1,
b0 -
1$
#10
0$
#11
b1 -
1$
#12
0$
#13
b10 -
1$
#14
0$
#15
b11 -
1$
#16
0$
#17
0,
b0 -
1$
#18
0$
#19
b1 -
1$
#20
0$
#21
b10 -
1$
#22
0$
#23
b11 -
1$
#24
0$
#25
b1 #
b1 *
b1 3
b1 6
1,
b0 -
1$
#26
0$
#27
b1 -
1$
#28
0$
#29
b10 -
1$
#30
0$
#31
b11 -
1$
#32
0$
#33
0,
b0 -
1$
#34
0$
#35
b1 -
1$
#36
0$
#37
b10 -
1$
#38
0$
#39
b11 -
1$
#40
0$
#41
b10 #
b10 *
b10 3
b10 6
1,
b0 -
1$
#42
0$
#43
b1 -
1$
#44
0$
#45
b10 -
1$
#46
0$
#47
b11 -
1$
#48
0$
#49
0,
b0 -
1$
#50
0$
#51
b1 -
1$
#52
0$
#53
b10 -
1$
#54
0$
#55
b11 -
1$
#56
0$
#57
b11 #
b11 *
b11 3
b11 6
1,
b0 -
1$
#58
0$
#59
b1 -
1$
#60
0$
#61
b10 -
1$
#62
0$
#63
b11 -
1$
#64
0$
#65
0,
b0 -
1$
#66
0$
#67
b1 -
1$
#68
0$
#69
b10 -
1$
#70
0$
#71
b11 -
1$
#72
0$
#73
b100 #
b100 *
b100 3
b100 6
1,
b0 -
1$
#74
0$
#75
b1 -
1$
#76
0$
#77
b10 -
1$
#78
0$
#79
b11 -
1$
#80
0$
#81
0,
b0 -
1$
#82
0$
#83
b1 -
1$
#84
0$
#85
b10 -
1$
#86
0$
#87
b11 -
1$
#88
0$
#89
b101 #
b101 *
b101 3
b101 6
1,
b0 -
1$
#90
0$
#91
b1 -
1$
#92
0$
#93
b10 -
1$
#94
0$
#95
b11 -
1$
#96
0$
#97
0,
b0 -
1$
#98
0$
#99
b1 -
1$
#100
0$
#101
b10 -
1$
#102
0$
#103
b11 -
1$
#104
0$
#105
b110 #
b110 *
b110 3
b110 6
1,
b0 -
1$
#106
0$
#107
b1 -
1$
#108
0$
#109
b10 -
1$
#110
0$
#111
b11 -
1$
#112
0$
#113
0,
b0 -
1$
#114
0$
#115
b1 -
1$
#116
0$
#117
b10 -
1$
#118
0$
#119
b11 -
1$
#120
0$
#121
b111 #
b111 *
b111 3
b111 6
1,
b0 -
1$
#122
0$
#123
b1 -
1$
#124
0$
#125
b10 -
1$
#126
0$
#127
b11 -
1$
#128
0$
#129
0,
b0 -
1$
#130
0$
#131
b1 -
1$
#132
0$
#133
b10 -
1$
#134
0$
#135
b11 -
1$
#136
0$
#137
b1000 #
b1000 *
b1000 3
b1000 6
1,
b0 -
1$
#138
0$
#139
b1 -
1$
#140
0$
#141
b10 -
1$
#142
0$
#143
b11 -
1$
#144
0$
#145
0,
b0 -
1$
#146
0$
#147
b1 -
1$
#148
0$
#149
b10 -
1$
#150
0$
#151
b11 -
1$
#152
0$
#153
b1001 #
b1001 *
b1001 3
b1001 6
1,
b0 -
1$
#154
0$
#155
b1 -
1$
#156
0$
#157
b10 -
1$
#158
0$
#159
b11 -
1$
#160
0$
#161
0,
b0 -
1$
#162
0$
#163
b1 -
1$
#164
0$
#165
b10 -
1$
#166
0$
#167
b11 -
1$
#168
0$
#169
b0 #
b0 *
b0 3
b0 6
b1 "
b1 )
b1 4
b1 7
1,
b0 -
1$
#170
0$
#171
b1 -
1$
#172
0$
#173
b10 -
1$
#174
0$
#175
b11 -
1$
#176
0$
#177
0,
b0 -
1$
#178
0$
#179
b1 -
1$
#180
0$
#181
b10 -
1$
#182
0$
#183
b11 -
1$
#184
0$
#185
b1 #
b1 *
b1 3
b1 6
1,
b0 -
1$
#186
0$
#187
b1 -
1$
#188
0$
#189
b10 -
1$
#190
0$
#191
b11 -
1$
#192
0$
#193
0,
b0 -
1$
#194
0$
#195
b1 -
1$
#196
0$
#197
b10 -
1$
#198
0$
#199
b11 -
1$
#200
0$
#201
b10 #
b10 *
b10 3
b10 6
1,
b0 -
1$
#202
0$
#203
b1 -
1$
#204
0$
#205
b10 -
1$
#206
0$
#207
b11 -
1$
#208
0$
#209
0,
b0 -
1$
#210
0$
#211
b1 -
1$
#212
0$
#213
b10 -
1$
#214
0$
#215
b11 -
1$
#216
0$
#217
b11 #
b11 *
b11 3
b11 6
1,
b0 -
1$
#218
0$
#219
b1 -
1$
#220
0$
#221
b10 -
1$
#222
0$
#223
b11 -
1$
#224
0$
#225
0,
b0 -
1$
#226
0$
#227
b1 -
1$
#228
0$
#229
b10 -
1$
#230
0$
#231
b11 -
1$
#232
0$
#233
b100 #
b100 *
b100 3
b100 6
1,
b0 -
1$
#234
0$
#235
b1 -
1$
#236
0$
#237
b10 -
1$
#238
0$
#239
b11 -
1$
#240
0$
#241
0,
b0 -
1$
#242
0$
#243
b1 -
1$
#244
0$
#245
b10 -
1$
#246
0$
#247
b11 -
1$
#248
0$
#249
b101 #
b101 *
b101 3
b101 6
1,
b0 -
1$
#250
0$
#251
b1 -
1$
#252
0$
#253
b10 -
1$
#254
0$
#255
b11 -
1$
#256
0$
#257
0,
b0 -
1$
#258
0$
#259
b1 -
1$
#260
0$
#261
b10 -
1$
#262
0$
#263
b11 -
1$
#264
0$
#265
b110 #
b110 *
b110 3
b110 6
1,
b0 -
1$
#266
0$
#267
b1 -
1$
#268
0$
#269
b10 -
1$
#270
0$
#271
b11 -
1$
#272
0$
#273
0,
b0 -
1$
#274
0$
#275
b1 -
1$
#276
0$
#277
b10 -
1$
#278
0$
#279
b11 -
1$
#280
0$
#281
b111 #
b111 *
b111 3
b111 6
1,
b0 -
1$
#282
0$
#283
b1 -
1$
#284
0$
#285
b10 -
1$
#286
0$
#287
b11 -
1$
#288
0$
#289
0,
b0 -
1$
#290
0$
#291
b1 -
1$
#292
0$
#293
b10 -
1$
#294
0$
#295
b11 -
1$
#296
0$
#297
b1000 #
b1000 *
b1000 3
b1000 6
1,
b0 -
1$
#298
0$
#299
b1 -
1$
#300
0$
#301
b10 -
1$
#302
0$
#303
b11 -
1$
#304
0$
#305
0,
b0 -
1$
#306
0$
#307
b1 -
1$
#308
0$
#309
b10 -
1$
#310
0$
#311
b11 -
1$
#312
0$
#313
b1001 #
b1001 *
b1001 3
b1001 6
1,
b0 -
1$
#314
0$
#315
b1 -
1$
#316
0$
#317
b10 -
1$
#318
0$
#319
b11 -
1$
#320
0$
#321
0,
b0 -
1$
#322
0$
#323
b1 -
1$
#324
0$
#325
b10 -
1$
#326
0$
#327
b11 -
1$
#328
0$
#329
b0 #
b0 *
b0 3
b0 6
b10 "
b10 )
b10 4
b10 7
1,
b0 -
1$
#330
0$
#331
b1 -
1$
#332
0$
#333
b10 -
1$
#334
0$
#335
b11 -
1$
#336
0$
#337
0,
b0 -
1$
#338
0$
#339
b1 -
1$
#340
0$
#341
b10 -
1$
#342
0$
#343
b11 -
1$
#344
0$
#345
b1 #
b1 *
b1 3
b1 6
1,
b0 -
1$
#346
0$
#347
b1 -
1$
#348
0$
#349
b10 -
1$
#350
0$
#351
b11 -
1$
#352
0$
#353
0,
b0 -
1$
#354
0$
#355
b1 -
1$
#356
0$
#357
b10 -
1$
#358
0$
#359
b11 -
1$
#360
0$
#361
b10 #
b10 *
b10 3
b10 6
1,
b0 -
1$
#362
0$
#363
b1 -
1$
#364
0$
#365
b10 -
1$
#366
0$
#367
b11 -
1$
#368
0$
#369
0,
b0 -
1$
#370
0$
#371
b1 -
1$
#372
0$
#373
b10 -
1$
#374
0$
#375
b11 -
1$
#376
0$
#377
b11 #
b11 *
b11 3
b11 6
1,
b0 -
1$
#378
0$
#379
b1 -
1$
#380
0$
#381
b10 -
1$
#382
0$
#383
b11 -
1$
#384
0$
#385
0,
b0 -
1$
#386
0$
#387
b1 -
1$
#388
0$
#389
b10 -
1$
#390
0$
#391
b11 -
1$
#392
0$
#393
b100 #
b100 *
b100 3
b100 6
1,
b0 -
1$
#394
0$
#395
b1 -
1$
#396
0$
#397
b10 -
1$
#398
0$
#399
b11 -
1$
#400
0$
#401
0,
b0 -
1$
#402
0$
#403
b1 -
1$
#404
0$
#405
b10 -
1$
#406
0$
#407
b11 -
1$
#408
0$
#409
b101 #
b101 *
b101 3
b101 6
1,
b0 -
1$
#410
0$
#411
b1 -
1$
#412
0$
#413
b10 -
1$
#414
0$
#415
b11 -
1$
#416
0$
#417
0,
b0 -
1$
#418
0$
#419
b1 -
1$
#420
0$
#421
b10 -
1$
#422
0$
#423
b11 -
1$
#424
0$
#425
b110 #
b110 *
b110 3
b110 6
1,
b0 -
1$
#426
0$
#427
b1 -
1$
#428
0$
#429
b10 -
1$
#430
0$
#431
b11 -
1$
#432
0$
#433
0,
b0 -
1$
#434
0$
#435
b1 -
1$
#436
0$
#437
b10 -
1$
#438
0$
#439
b11 -
1$
#440
0$
#441
b111 #
b111 *
b111 3
b111 6
1,
b0 -
1$
#442
0$
#443
b1 -
1$
#444
0$
#445
b10 -
1$
#446
0$
#447
b11 -
1$
#448
0$
#449
0,
b0 -
1$
#450
0$
#451
b1 -
1$
#452
0$
#453
b10 -
1$
#454
0$
#455
b11 -
1$
#456
0$
#457
b1000 #
b1000 *
b1000 3
b1000 6
1,
b0 -
1$
#458
0$
#459
b1 -
1$
#460
0$
#461
b10 -
1$
#462
0$
#463
b11 -
1$
#464
0$
#465
0,
b0 -
1$
#466
0$
#467
b1 -
1$
#468
0$
#469
b10 -
1$
#470
0$
#471
b11 -
1$
#472
0$
#473
b1001 #
b1001 *
b1001 3
b1001 6
1,
b0 -
1$
#474
0$
#475
b1 -
1$
#476
0$
#477
b10 -
1$
#478
0$
#479
b11 -
1$
#480
0$
#481
0,
b0 -
1$
#482
0$
#483
b1 -
1$
#484
0$
#485
b10 -
1$
#486
0$
#487
b11 -
1$
#488
0$
#489
b0 #
b0 *
b0 3
b0 6
b11 "
b11 )
b11 4
b11 7
1,
b0 -
1$
#490
0$
#491
b1 -
1$
#492
0$
#493
b10 -
1$
#494
0$
#495
b11 -
1$
#496
0$
#497
0,
b0 -
1$
#498
0$
#499
b1 -
1$
#500
0$
#501
b10 -
1$
#502
0$
#503
b11 -
1$
#504
0$
#505
b1 #
b1 *
b1 3
b1 6
1,
b0 -
1$
#506
0$
#507
b1 -
1$
#508
0$
#509
b10 -
1$
#510
0$
#511
b11 -
1$
#512
0$
#513
0,
b0 -
1$
#514
0$
#515
b1 -
1$
#516
0$
#517
b10 -
1$
#518
0$
#519
b11 -
1$
#520
0$
#521
b10 #
b10 *
b10 3
b10 6
1,
b0 -
1$
#522
0$
#523
b1 -
1$
#524
0$
#525
b10 -
1$
#526
0$
#527
b11 -
1$
#528
0$
#529
0,
b0 -
1$
#530
0$
#531
b1 -
1$
#532
0$
#533
b10 -
1$
#534
0$
#535
b11 -
1$
#536
0$
#537
b11 #
b11 *
b11 3
b11 6
1,
b0 -
1$
#538
0$
#539
b1 -
1$
#540
0$
#541
b10 -
1$
#542
0$
#543
b11 -
1$
#544
0$
#545
0,
b0 -
1$
#546
0$
#547
b1 -
1$
#548
0$
#549
b10 -
1$
#550
0$
#551
b11 -
1$
#552
0$
#553
b100 #
b100 *
b100 3
b100 6
1,
b0 -
1$
#554
0$
#555
b1 -
1$
#556
0$
#557
b10 -
1$
#558
0$
#559
b11 -
1$
#560
0$
#561
0,
b0 -
1$
#562
0$
#563
b1 -
1$
#564
0$
#565
b10 -
1$
#566
0$
#567
b11 -
1$
#568
0$
#569
b101 #
b101 *
b101 3
b101 6
1,
b0 -
1$
#570
0$
#571
b1 -
1$
#572
0$
#573
b10 -
1$
#574
0$
#575
b11 -
1$
#576
0$
#577
0,
b0 -
1$
#578
0$
#579
b1 -
1$
#580
0$
#581
b10 -
1$
#582
0$
#583
b11 -
1$
#584
0$
#585
b110 #
b110 *
b110 3
b110 6
1,
b0 -
1$
#586
0$
#587
b1 -
1$
#588
0$
#589
b10 -
1$
#590
0$
#591
b11 -
1$
#592
0$
#593
0,
b0 -
1$
#594
0$
#595
b1 -
1$
#596
0$
#597
b10 -
1$
#598
0$
#599
b11 -
1$
#600
0$
#601
b111 #
b111 *
b111 3
b111 6
1,
b0 -
1$
#602
0$
#603
b1 -
1$
#604
0$
#605
b10 -
1$
#606
0$
#607
b11 -
1$
#608
0$
#609
0,
b0 -
1$
#610
0$
#611
b1 -
1$
#612
0$
#613
b10 -
1$
#614
0$
#615
b11 -
1$
#616
0$
#617
b1000 #
b1000 *
b1000 3
b1000 6
1,
b0 -
1$
#618
0$
#619
b1 -
1$
#620
0$
#621
b10 -
1$
#622
0$
#623
b11 -
1$
#624
0$
#625
0,
b0 -
1$
#626
0$
#627
b1 -
1$
#628
0$
#629
b10 -
1$
#630
0$
#631
b11 -
1$
#632
0$
#633
b1001 #
b1001 *
b1001 3
b1001 6
1,
b0 -
1$
#634
0$
#635
b1 -
1$
#636
0$
#637
b10 -
1$
#638
0$
#639
b11 -
1$
#640
0$
#641
0,
b0 -
1$
#642
0$
#643
b1 -
1$
#644
0$
#645
b10 -
1$
#646
0$
#647
b11 -
1$
#648
0$
#649
b0 #
b0 *
b0 3
b0 6
b100 "
b100 )
b100 4
b100 7
1,
b0 -
1$
#650
0$
#651
b1 -
1$
#652
0$
#653
b10 -
1$
#654
0$
#655
b11 -
1$
#656
0$
#657
0,
b0 -
1$
#658
0$
#659
b1 -
1$
#660
0$
#661
b10 -
1$
#662
0$
#663
b11 -
1$
#664
0$
#665
b1 #
b1 *
b1 3
b1 6
1,
b0 -
1$
#666
0$
#667
b1 -
1$
#668
0$
#669
b10 -
1$
#670
0$
#671
b11 -
1$
#672
0$
#673
0,
b0 -
1$
#674
0$
#675
b1 -
1$
#676
0$
#677
b10 -
1$
#678
0$
#679
b11 -
1$
#680
0$
#681
b10 #
b10 *
b10 3
b10 6
1,
b0 -
1$
#682
0$
#683
b1 -
1$
#684
0$
#685
b10 -
1$
#686
0$
#687
b11 -
1$
#688
0$
#689
0,
b0 -
1$
#690
0$
#691
b1 -
1$
#692
0$
#693
b10 -
1$
#694
0$
#695
b11 -
1$
#696
0$
#697
b11 #
b11 *
b11 3
b11 6
1,
b0 -
1$
#698
0$
#699
b1 -
1$
#700
0$
#701
b10 -
1$
#702
0$
#703
b11 -
1$
#704
0$
#705
0,
b0 -
1$
#706
0$
#707
b1 -
1$
#708
0$
#709
b10 -
1$
#710
0$
#711
b11 -
1$
#712
0$
#713
b100 #
b100 *
b100 3
b100 6
1,
b0 -
1$
#714
0$
#715
b1 -
1$
#716
0$
#717
b10 -
1$
#718
0$
#719
b11 -
1$
#720
0$
#721
0,
b0 -
1$
#722
0$
#723
b1 -
1$
#724
0$
#725
b10 -
1$
#726
0$
#727
b11 -
1$
#728
0$
#729
b101 #
b101 *
b101 3
b101 6
1,
b0 -
1$
#730
0$
#731
b1 -
1$
#732
0$
#733
b10 -
1$
#734
0$
#735
b11 -
1$
#736
0$
#737
0,
b0 -
1$
#738
0$
#739
b1 -
1$
#740
0$
#741
b10 -
1$
#742
0$
#743
b11 -
1$
#744
0$
#745
b110 #
b110 *
b110 3
b110 6
1,
b0 -
1$
#746
0$
#747
b1 -
1$
#748
0$
#749
b10 -
1$
#750
0$
#751
b11 -
1$
#752
0$
#753
0,
b0 -
1$
#754
0$
#755
b1 -
1$
#756
0$
#757
b10 -
1$
#758
0$
#759
b11 -
1$
#760
0$
#761
b111 #
b111 *
b111 3
b111 6
1,
b0 -
1$
#762
0$
#763
b1 -
1$
#764
0$
#765
b10 -
1$
#766
0$
#767
b11 -
1$
#768
0$
#769
0,
b0 -
1$
#770
0$
#771
b1 -
1$
#772
0$
#773
b10 -
1$
#774
0$
#775
b11 -
1$
#776
0$
#777
b1000 #
b1000 *
b1000 3
b1000 6
1,
b0 -
1$
#778
0$
#779
b1 -
1$
#780
0$
#781
b10 -
1$
#782
0$
#783
b11 -
1$
#784
0$
#785
0,
b0 -
1$
#786
0$
#787
b1 -
1$
#788
0$
#789
b10 -
1$
#790
0$
#791
b11 -
1$
#792
0$
#793
b1001 #
b1001 *
b1001 3
b1001 6
1,
b0 -
1$
#794
0$
#795
b1 -
1$
#796
0$
#797
b10 -
1$
#798
0$
#799
b11 -
1$
#800
0$
#801
0,
b0 -
1$
#802
b10 1
0$
1'
0&
#803
b1 -
1$
#804
0$
#805
b10 -
1$
#806
0$
#807
b11 -
1$
#808
0$
#809
b0 #
b0 *
b0 3
b0 6
b101 "
b101 )
b101 4
b101 7
0+
b10 2
1,
b0 -
1$
#810
0$
#811
b1 -
1$
#812
0$
#813
b10 -
1$
#814
0$
#815
b11 -
1$
#816
0$
#817
0,
b0 -
1$
#818
0$
#819
b1 -
1$
#820
0$
#821
b10 -
1$
#822
0$
#823
b11 -
1$
#824
0$
#825
1,
b0 -
1$
#826
0$
#827
b1 -
1$
#828
0$
#829
b10 -
1$
#830
0$
#831
b11 -
1$
#832
0$
#833
0,
b0 -
1$
#834
0$
#835
b1 -
1$
#836
0$
#837
b10 -
1$
#838
0$
#839
b11 -
1$
#840
0$
#841
1,
b0 -
1$
#842
0$
#843
b1 -
1$
#844
0$
#845
b10 -
1$
#846
0$
#847
b11 -
1$
#848
0$
#849
0,
b0 -
1$
#850
0$
#851
b1 -
1$
#852
0$
#853
b10 -
1$
#854
0$
#855
b11 -
1$
#856
0$
#857
1,
b0 -
1$
#858
0$
#859
b1 -
1$
#860
0$
#861
b10 -
1$
#862
0$
#863
b11 -
1$
#864
0$
#865
0,
b0 -
1$
#866
0$
#867
b1 -
1$
#868
0$
#869
b10 -
1$
#870
0$
#871
b11 -
1$
#872
0$
#873
1,
b0 -
1$
#874
0$
#875
b1 -
1$
#876
0$
#877
b10 -
1$
#878
0$
#879
b11 -
1$
#880
0$
#881
0,
b0 -
1$
#882
0$
#883
b1 -
1$
#884
0$
#885
b10 -
1$
#886
0$
#887
b11 -
1$
#888
0$
#889
1,
b0 -
1$
#890
0$
#891
b1 -
1$
#892
0$
#893
b10 -
1$
#894
0$
#895
b11 -
1$
#896
0$
#897
0,
b0 -
1$
#898
0$
#899
b1 -
1$
#900
0$
#901
b10 -
1$
#902
0$
#903
b11 -
1$
#904
0$
#905
1,
b0 -
1$
#906
0$
#907
b1 -
1$
#908
0$
#909
b10 -
1$
#910
0$
#911
b11 -
1$
#912
0$
#913
0,
b0 -
1$
#914
0$
#915
b1 -
1$
#916
0$
#917
b10 -
1$
#918
0$
#919
b11 -
1$
#920
0$
#921
1,
b0 -
1$
#922
0$
#923
b1 -
1$
#924
0$
#925
b10 -
1$
#926
0$
#927
b11 -
1$
#928
0$
#929
0,
b0 -
1$
#930
0$
#931
b1 -
1$
#932
0$
#933
b10 -
1$
#934
0$
#935
b11 -
1$
#936
0$
#937
1,
b0 -
1$
#938
0$
#939
b1 -
1$
#940
0$
#941
b10 -
1$
#942
0$
#943
b11 -
1$
#944
0$
#945
0,
b0 -
1$
#946
0$
#947
b1 -
1$
#948
0$
#949
b10 -
1$
#950
0$
#951
b11 -
1$
#952
0$
#953
1,
b0 -
1$
#954
0$
#955
b1 -
1$
#956
0$
#957
b10 -
1$
#958
0$
#959
b11 -
1$
#960
0$
#961
0,
b0 -
1$
#962
0$
#963
b1 -
1$
#964
0$
#965
b10 -
1$
#966
0$
#967
b11 -
1$
#968
0$
#969
1,
b0 -
1$
#970
0$
#971
b1 -
1$
#972
0$
#973
b10 -
1$
#974
0$
#975
b11 -
1$
#976
0$
#977
0,
b0 -
1$
#978
0$
#979
b1 -
1$
#980
0$
#981
b10 -
1$
#982
0$
#983
b11 -
1$
#984
0$
#985
1,
b0 -
1$
#986
0$
#987
b1 -
1$
#988
0$
#989
b10 -
1$
#990
0$
#991
b11 -
1$
#992
0$
#993
0,
b0 -
1$
#994
0$
#995
b1 -
1$
#996
0$
#997
b10 -
1$
#998
0$
#999
b11 -
1$
#1000
0$
#1001
1,
b0 -
1$
#1002
b1 1
0$
0'
1&
#1003
b1 -
1$
#1004
0$
#1005
b10 -
1$
#1006
0$
#1007
b11 -
1$
#1008
0$
#1009
0,
b0 -
1$
#1010
0$
#1011
b1 -
1$
#1012
0$
#1013
b10 -
1$
#1014
0$
#1015
b11 -
1$
#1016
0$
#1017
1+
b1 2
1,
b0 -
1$
#1018
0$
#1019
b1 -
1$
#1020
0$
#1021
b10 -
1$
#1022
0$
#1023
b11 -
1$
#1024
0$
#1025
0,
b0 -
1$
#1026
0$
#1027
b1 -
1$
#1028
0$
#1029
b10 -
1$
#1030
0$
#1031
b11 -
1$
#1032
0$
#1033
b1 #
b1 *
b1 3
b1 6
1,
b0 -
1$
#1034
0$
#1035
b1 -
1$
#1036
0$
#1037
b10 -
1$
#1038
0$
#1039
b11 -
1$
#1040
0$
#1041
0,
b0 -
1$
#1042
0$
#1043
b1 -
1$
#1044
0$
#1045
b10 -
1$
#1046
0$
#1047
b11 -
1$
#1048
0$
#1049
b10 #
b10 *
b10 3
b10 6
1,
b0 -
1$
#1050
0$
#1051
b1 -
1$
#1052
0$
#1053
b10 -
1$
#1054
0$
#1055
b11 -
1$
#1056
0$
#1057
0,
b0 -
1$
#1058
0$
#1059
b1 -
1$
#1060
0$
#1061
b10 -
1$
#1062
0$
#1063
b11 -
1$
#1064
0$
#1065
b11 #
b11 *
b11 3
b11 6
1,
b0 -
1$
#1066
0$
#1067
b1 -
1$
#1068
0$
#1069
b10 -
1$
#1070
0$
#1071
b11 -
1$
#1072
0$
#1073
0,
b0 -
1$
#1074
0$
#1075
b1 -
1$
#1076
0$
#1077
b10 -
1$
#1078
0$
#1079
b11 -
1$
#1080
0$
#1081
b100 #
b100 *
b100 3
b100 6
1,
b0 -
1$
#1082
0$
#1083
b1 -
1$
#1084
0$
#1085
b10 -
1$
#1086
0$
#1087
b11 -
1$
#1088
0$
#1089
0,
b0 -
1$
#1090
0$
#1091
b1 -
1$
#1092
0$
#1093
b10 -
1$
#1094
0$
#1095
b11 -
1$
#1096
0$
#1097
b101 #
b101 *
b101 3
b101 6
1,
b0 -
1$
#1098
0$
#1099
b1 -
1$
#1100
0$
#1101
b10 -
1$
#1102
0$
#1103
b11 -
1$
#1104
0$
#1105
0,
b0 -
1$
#1106
0$
#1107
b1 -
1$
#1108
0$
#1109
b10 -
1$
#1110
0$
#1111
b11 -
1$
#1112
0$
#1113
b110 #
b110 *
b110 3
b110 6
1,
b0 -
1$
#1114
0$
#1115
b1 -
1$
#1116
0$
#1117
b10 -
1$
#1118
0$
#1119
b11 -
1$
#1120
0$
#1121
0,
b0 -
1$
#1122
0$
#1123
b1 -
1$
#1124
0$
#1125
b10 -
1$
#1126
0$
#1127
b11 -
1$
#1128
0$
#1129
b111 #
b111 *
b111 3
b111 6
1,
b0 -
1$
#1130
0$
#1131
b1 -
1$
#1132
0$
#1133
b10 -
1$
#1134
0$
#1135
b11 -
1$
#1136
0$
#1137
0,
b0 -
1$
#1138
0$
#1139
b1 -
1$
#1140
0$
#1141
b10 -
1$
#1142
0$
#1143
b11 -
1$
#1144
0$
#1145
b1000 #
b1000 *
b1000 3
b1000 6
1,
b0 -
1$
#1146
0$
#1147
b1 -
1$
#1148
0$
#1149
b10 -
1$
#1150
0$
#1151
b11 -
1$
#1152
0$
#1153
0,
b0 -
1$
#1154
0$
#1155
b1 -
1$
#1156
0$
#1157
b10 -
1$
#1158
0$
#1159
b11 -
1$
#1160
0$
#1161
b1001 #
b1001 *
b1001 3
b1001 6
1,
b0 -
1$
#1162
0$
#1163
b1 -
1$
#1164
0$
#1165
b10 -
1$
#1166
0$
#1167
b11 -
1$
#1168
0$
#1169
0,
b0 -
1$
#1170
0$
#1171
b1 -
1$
#1172
0$
#1173
b10 -
1$
#1174
0$
#1175
b11 -
1$
#1176
0$
#1177
b0 #
b0 *
b0 3
b0 6
b110 "
b110 )
b110 4
b110 7
1,
b0 -
1$
#1178
0$
#1179
b1 -
1$
#1180
0$
#1181
b10 -
1$
#1182
0$
#1183
b11 -
1$
#1184
0$
#1185
0,
b0 -
1$
#1186
0$
