Stopwatch/watch.sv
module watch (
    input  logic       clk,
    input  logic       rst,
    input  logic       en,
    output logic [3:0] y2,
    output logic [3:0] y1,
    output logic [3:0] y0
);

  logic [3:0] cnt2;
  logic [3:0] cnt1;
  logic [3:0] cnt0;

  always_ff @(posedge clk or posedge rst) begin : counter
    if (rst) begin
      cnt0 <= '0;  // Ones
      cnt1 <= '0;  // Tens
      cnt2 <= '0;  // Hundreds
    end else if (en) begin
      if (cnt0 != 9) cnt0 <= cnt0 + 1;
      else if (cnt0 == 9 && cnt1 != 9) begin
        cnt1 <= cnt1 + 1;
        cnt0 <= 0;
      end else if (cnt0 == 9 && cnt1 == 9 && cnt2 != 9) begin
        cnt2 <= cnt2 + 1;
        cnt1 <= 0;
        cnt0 <= 0;
      end else begin
        cnt0 <= '0;
        cnt1 <= '0;
        cnt2 <= '0;
      end
    end
  end

  assign y2 = cnt2;
  assign y1 = cnt1;
  assign y0 = cnt0;
endmodule

Stopwatch/watch_tb.sv
module watch_tb;
  logic clk;
  logic rst;
  logic en;
  logic [3:0] y2;
  logic [3:0] y1;
  logic [3:0] y0;

  watch uut (
      .clk(clk),
      .rst(rst),
      .en (en),
      .y2 (y2),
      .y1 (y1),
      .y0 (y0)
  );

  initial begin
    $dumpfile("watch.vcd");
    $dumpvars(0, watch_tb);
  end

  always #1 clk = ~clk;

  initial begin
    clk = 0;
    rst = 1;
    en  = 0;
    #2;
    rst = 0;
    en  = 1;
    #500;
    en = 0;
    #500;
    en = 1;
    #4000;
    $finish;
  end
endmodule

Stopwatch/watch.vcd
$date
	Mon Jun 30 15:36:20 2025
$end
$version
	Icarus Verilog
$end
$timescale
	1s
$end
$scope module watch_tb $end
$var wire 4 ! y2 [3:0] $end
$var wire 4 " y1 [3:0] $end
$var wire 4 # y0 [3:0] $end
$var reg 1 $ clk $end
$var reg 1 % en $end
$var reg 1 & rst $end
$scope module uut $end
$var wire 1 $ clk $end
$var wire 1 % en $end
$var wire 1 & rst $end
$var wire 4 ' y0 [3:0] $end
$var wire 4 ( y1 [3:0] $end
$var wire 4 ) y2 [3:0] $end
$var reg 4 * cnt0 [3:0] $end
$var reg 4 + cnt1 [3:0] $end
$var reg 4 , cnt2 [3:0] $end
$scope begin counter $end
$upscope $end
$upscope $end
$upscope $end
$enddefinitions $end
$comment Show the parameter values. $end
$dumpall
$end
#0
$dumpvars
b0 ,
b0 +
b0 *
b0 )
b0 (
b0 '
1&
0%
0$
b0 #
b0 "
b0 !
$end
#1
1$
#2
0$
1%
0&
#3
b1 #
b1 '
b1 *
1$
#4
0$
#5
b10 #
b10 '
b10 *
1$
#6
0$
#7
b11 #
b11 '
b11 *
1$
#8
0$
#9
b100 #
b100 '
b100 *
1$
#10
0$
#11
b101 #
b101 '
b101 *
1$
#12
0$
#13
b110 #
b110 '
b110 *
1$
#14
0$
#15
b111 #
b111 '
b111 *
1$
#16
0$
#17
b1000 #
b1000 '
b1000 *
1$
#18
0$
#19
b1001 #
b1001 '
b1001 *
1$
#20
0$
#21
b0 #
b0 '
b0 *
b1 "
b1 (
b1 +
1$
#22
0$
#23
b1 #
b1 '
b1 *
1$
#24
0$
#25
b10 #
b10 '
b10 *
1$
#26
0$
#27
b11 #
b11 '
b11 *
1$
#28
0$
#29
b100 #
b100 '
b100 *
1$
#30
0$
#31
b101 #
b101 '
b101 *
1$
#32
0$
#33
b110 #
b110 '
b110 *
1$
#34
0$
#35
b111 #
b111 '
b111 *
1$
#36
0$
#37
b1000 #
b1000 '
b1000 *
1$
#38
0$
#39
b1001 #
b1001 '
b1001 *
1$
#40
0$
#41
b0 #
b0 '
b0 *
b10 "
b10 (
b10 +
1$
#42
0$
#43
b1 #
b1 '
b1 *
1$
#44
0$
#45
b10 #
b10 '
b10 *
1$
#46
0$
#47
b11 #
b11 '
b11 *
1$
#48
0$
#49
b100 #
b100 '
b100 *
1$
#50
0$
#51
b101 #
b101 '
b101 *
1$
#52
0$
#53
b110 #
b110 '
b110 *
1$
#54
0$
#55
b111 #
b111 '
b111 *
1$
#56
0$
#57
b1000 #
b1000 '
b1000 *
1$
#58
0$
#59
b1001 #
b1001 '
b1001 *
1$
#60
0$
#61
b0 #
b0 '
b0 *
b11 "
b11 (
b11 +
1$
#62
0$
#63
b1 #
b1 '
b1 *
1$
#64
0$
#65
b10 #
b10 '
b10 *
1$
#66
0$
#67
b11 #
b11 '
b11 *
1$
#68
0$
#69
b100 #
b100 '
b100 *
1$
#70
0$
#71
b101 #
b101 '
b101 *
1$
#72
0$
#73
b110 #
b110 '
b110 *
1$
#74
0$
#75
b111 #
b111 '
b111 *
1$
#76
0$
#77
b1000 #
b1000 '
b1000 *
1$
#78
0$
#79
b1001 #
b1001 '
b1001 *
1$
#80
0$
#81
b0 #
b0 '
b0 *
b100 "
b100 (
b100 +
1$
#82
0$
#83
b1 #
b1 '
b1 *
1$
#84
0$
#85
b10 #
b10 '
b10 *
1$
#86
0$
#87
b11 #
b11 '
b11 *
1$
#88
0$
#89
b100 #
b100 '
b100 *
1$
#90
0$
#91
b101 #
b101 '
b101 *
1$
#92
0$
#93
b110 #
b110 '
b110 *
1$
#94
0$
#95
b111 #
b111 '
b111 *
1$
#96
0$
#97
b1000 #
b1000 '
b1000 *
1$
#98
0$
#99
b1001 #
b1001 '
b1001 *
1$
#100
0$
#101
b0 #
b0 '
b0 *
b101 "
b101 (
b101 +
1$
#102
0$
#103
b1 #
b1 '
b1 *
1$
#104
0$
#105
b10 #
b10 '
b10 *
1$
#106
0$
#107
b11 #
b11 '
b11 *
1$
#108
0$
#109
b100 #
b100 '
b100 *
1$
#110
0$
#111
b101 #
b101 '
b101 *
1$
#112
0$
#113
b110 #
b110 '
b110 *
1$
#114
0$
#115
b111 #
b111 '
b111 *
1$
#116
0$
#117
b1000 #
b1000 '
b1000 *
1$
#118
0$
#119
b1001 #
b1001 '
b1001 *
1$
#120
0$
#121
b0 #
b0 '
b0 *
b110 "
b110 (
b110 +
1$
#122
0$
#123
b1 #
b1 '
b1 *
1$
#124
0$
#125
b10 #
b10 '
b10 *
1$
#126
0$
#127
b11 #
b11 '
b11 *
1$
#128
0$
#129
b100 #
b100 '
b100 *
1$
#130
0$
#131
b101 #
b101 '
b101 *
1$
#132
0$
#133
b110 #
b110 '
b110 *
1$
#134
0$
#135
b111 #
b111 '
b111 *
1$
#136
0$
#137
b1000 #
b1000 '
b1000 *
1$
#138
0$
#139
b1001 #
b1001 '
b1001 *
1$
#140
0$
#141
b0 #
b0 '
b0 *
b111 "
b111 (
b111 +
1$
#142
0$
#143
b1 #
b1 '
b1 *
1$
#144
0$
#145
b10 #
b10 '
b10 *
1$
#146
0$
#147
b11 #
b11 '
b11 *
1$
#148
0$
#149
b100 #
b100 '
b100 *
1$
#150
0$
#151
b101 #
b101 '
b101 *
1$
#152
0$
#153
b110 #
b110 '
b110 *
1$
#154
0$
#155
b111 #
b111 '
b111 *
1$
#156
0$
#157
b1000 #
b1000 '
b1000 *
1$
#158
0$
#159
b1001 #
b1001 '
b1001 *
1$
#160
0$
#161
b0 #
b0 '
b0 *
b1000 "
b1000 (
b1000 +
1$
#162
0$
#163
b1 #
b1 '
b1 *
1$
#164
0$
#165
b10 #
b10 '
b10 *
1$
#166
0$
#167
b11 #
b11 '
b11 *
1$
#168
0$
#169
b100 #
b100 '
b100 *
1$
#170
0$
#171
b101 #
b101 '
b101 *
1$
#172
0$
#173
b110 #
b110 '
b110 *
1$
#174
0$
#175
b111 #
b111 '
b111 *
1$
#176
0$
#177
b1000 #
b1000 '
b1000 *
1$
#178
0$
#179
b1001 #
b1001 '
b1001 *
1$
#180
0$
#181
b0 #
b0 '
b0 *
b1001 "
b1001 (
b1001 +
1$
#182
0$
#183
b1 #
b1 '
b1 *
1$
#184
0$
#185
b10 #
b10 '
b10 *
1$
#186
0$
#187
b11 #
b11 '
b11 *
1$
#188
0$
#189
b100 #
b100 '
b100 *
1$
#190
0$
#191
b101 #
b101 '
b101 *
1$
#192
0$
#193
b110 #
b110 '
b110 *
1$
#194
0$
#195
b111 #
b111 '
b111 *
1$
#196
0$
#197
b1000 #
b1000 '
b1000 *
1$
#198
0$
#199
b1001 #
b1001 '
b1001 *
1$
#200
0$
#201
b0 #
b0 '
b0 *
b0 "
b0 (
b0 +
b1 !
b1 )
b1 ,
1$
#202
0$
#203
b1 #
b1 '
b1 *
1$
#204
0$
#205
b10 #
b10 '
b10 *
1$
#206
0$
#207
b11 #
b11 '
b11 *
1$
#208
0$
#209
b100 #
b100 '
b100 *
1$
#210
0$
#211
b101 #
b101 '
b101 *
1$
#212
0$
#213
b110 #
b110 '
b110 *
1$
#214
0$
#215
b111 #
b111 '
b111 *
1$
#216
0$
#217
b1000 #
b1000 '
b1000 *
1$
#218
0$
#219
b1001 #
b1001 '
b1001 *
1$
#220
0$
#221
b0 #
b0 '
b0 *
b1 "
b1 (
b1 +
1$
#222
0$
#223
b1 #
b1 '
b1 *
1$
#224
0$
#225
b10 #
b10 '
b10 *
1$
#226
0$
#227
b11 #
b11 '
b11 *
1$
#228
0$
#229
b100 #
b100 '
b100 *
1$
#230
0$
#231
b101 #
b101 '
b101 *
1$
#232
0$
#233
b110 #
b110 '
b110 *
1$
#234
0$
#235
b111 #
b111 '
b111 *
1$
#236
0$
#237
b1000 #
b1000 '
b1000 *
1$
#238
0$
#239
b1001 #
b1001 '
b1001 *
1$
#240
0$
#241
b0 #
b0 '
b0 *
b10 "
b10 (
b10 +
1$
#242
0$
#243
b1 #
b1 '
b1 *
1$
#244
0$
#245
b10 #
b10 '
b10 *
1$
#246
0$
#247
b11 #
b11 '
b11 *
1$
#248
0$
#249
b100 #
b100 '
b100 *
1$
#250
0$
#251
b101 #
b101 '
b101 *
1$
#252
0$
#253
b110 #
b110 '
b110 *
1$
#254
0$
#255
b111 #
b111 '
b111 *
1$
#256
0$
#257
b1000 #
b1000 '
b1000 *
1$
#258
0$
#259
b1001 #
b1001 '
b1001 *
1$
#260
0$
#261
b0 #
b0 '
b0 *
b11 "
b11 (
b11 +
1$
#262
0$
#263
b1 #
b1 '
b1 *
1$
#264
0$
#265
b10 #
b10 '
b10 *
1$
#266
0$
#267
b11 #
b11 '
b11 *
1$
#268
0$
#269
b100 #
b100 '
b100 *
1$
#270
0$
#271
b101 #
b101 '
b101 *
1$
#272
0$
#273
b110 #
b110 '
b110 *
1$
#274
0$
#275
b111 #
b111 '
b111 *
1$
#276
0$
#277
b1000 #
b1000 '
b1000 *
1$
#278
0$
#279
b1001 #
b1001 '
b1001 *
1$
#280
0$
#281
b0 #
b0 '
b0 *
b100 "
b100 (
b100 +
1$
#282
0$
#283
b1 #
b1 '
b1 *
1$
#284
0$
#285
b10 #
b10 '
b10 *
1$
#286
0$
#287
b11 #
b11 '
b11 *
1$
#288
0$
#289
b100 #
b100 '
b100 *
1$
#290
0$
#291
b101 #
b101 '
b101 *
1$
#292
0$
#293
b110 #
b110 '
b110 *
1$
#294
0$
#295
b111 #
b111 '
b111 *
1$
#296
0$
#297
b1000 #
b1000 '
b1000 *
1$
#298
0$
#299
b1001 #
b1001 '
b1001 *
1$
#300
0$
#301
b0 #
b0 '
b0 *
b101 "
b101 (
b101 +
1$
#302
0$
#303
b1 #
b1 '
b1 *
1$
#304
0$
#305
b10 #
b10 '
b10 *
1$
#306
0$
#307
b11 #
b11 '
b11 *
1$
#308
0$
#309
b100 #
b100 '
b100 *
1$
#310
0$
#311
b101 #
b101 '
b101 *
1$
#312
0$
#313
b110 #
b110 '
b110 *
1$
#314
0$
#315
b111 #
b111 '
b111 *
1$
#316
0$
#317
b1000 #
b1000 '
b1000 *
1$
#318
0$
#319
b1001 #
b1001 '
b1001 *
1$
#320
0$
#321
b0 #
b0 '
b0 *
b110 "
b110 (
b110 +
1$
#322
0$
#323
b1 #
b1 '
b1 *
1$
#324
0$
#325
b10 #
b10 '
b10 *
1$
#326
0$
#327
b11 #
b11 '
b11 *
1$
#328
0$
#329
b100 #
b100 '
b100 *
1$
#330
0$
#331
b101 #
b101 '
b101 *
1$
#332
0$
#333
b110 #
b110 '
b110 *
1$
#334
0$
#335
b111 #
b111 '
b111 *
1$
#336
0$
#337
b1000 #
b1000 '
b1000 *
1$
#338
0$
#339
b1001 #
b1001 '
b1001 *
1$
#340
0$
#341
b0 #
b0 '
b0 *
b111 "
b111 (
b111 +
1$
#342
0$
#343
b1 #
b1 '
b1 *
1$
#344
0$
#345
b10 #
b10 '
b10 *
1$
#346
0$
#347
b11 #
b11 '
b11 *
1$
#348
0$
#349
b100 #
b100 '
b100 *
1$
#350
0$
#351
b101 #
b101 '
b101 *
1$
#352
0$
#353
b110 #
b110 '
b110 *
1$
#354
0$
#355
b111 #
b111 '
b111 *
1$
#356
0$
#357
b1000 #
b1000 '
b1000 *
1$
#358
0$
#359
b1001 #
b1001 '
b1001 *
1$
#360
0$
#361
b0 #
b0 '
b0 *
b1000 "
b1000 (
b1000 +
1$
#362
0$
#363
b1 #
b1 '
b1 *
1$
#364
0$
#365
b10 #
b10 '
b10 *
1$
#366
0$
#367
b11 #
b11 '
b11 *
1$
#368
0$
#369
b100 #
b100 '
b100 *
1$
#370
0$
#371
b101 #
b101 '
b101 *
1$
#372
0$
#373
b110 #
b110 '
b110 *
1$
#374
0$
#375
b111 #
b111 '
b111 *
1$
#376
0$
#377
b1000 #
b1000 '
b1000 *
1$
#378
0$
#379
b1001 #
b1001 '
b1001 *
1$
#380
0$
#381
b0 #
b0 '
b0 *
b1001 "
b1001 (
b1001 +
1$
#382
0$
#383
b1 #
b1 '
b1 *
1$
#384
0$
#385
b10 #
b10 '
b10 *
1$
#386
0$
#387
b11 #
b11 '
b11 *
1$
#388
0$
#389
b100 #
b100 '
b100 *
1$
#390
0$
#391
b101 #
b101 '
b101 *
1$
#392
0$
#393
b110 #
b110 '
b110 *
1$
#394
0$
#395
b111 #
b111 '
b111 *
1$
#396
0$
#397
b1000 #
b1000 '
b1000 *
1$
#398
0$
#399
b1001 #
b1001 '
b1001 *
1$
#400
0$
#401
b0 #
b0 '
b0 *
b0 "
b0 (
b0 +
b10 !
b10 )
b10 ,
1$
#402
0$
#403
b1 #
b1 '
b1 *
1$
#404
0$
#405
b10 #
b10 '
b10 *
1$
#406
0$
#407
b11 #
b11 '
b11 *
1$
#408
0$
#409
b100 #
b100 '
b100 *
1$
#410
0$
#411
b101 #
b101 '
b101 *
1$
#412
0$
#413
b110 #
b110 '
b110 *
1$
#414
0$
#415
b111 #
b111 '
b111 *
1$
#416
0$
#417
b1000 #
b1000 '
b1000 *
1$
#418
0$
#419
b1001 #
b1001 '
b1001 *
1$
#420
0$
#421
b0 #
b0 '
b0 *
b1 "
b1 (
b1 +
1$
#422
0$
#423
b1 #
b1 '
b1 *
1$
#424
0$
#425
b10 #
b10 '
b10 *
1$
#426
0$
#427
b11 #
b11 '
b11 *
1$
#428
0$
#429
b100 #
b100 '
b100 *
1$
#430
0$
#431
b101 #
b101 '
b101 *
1$
#432
0$
#433
b110 #
b110 '
b110 *
1$
#434
0$
#435
b111 #
b111 '
b111 *
1$
#436
0$
#437
b1000 #
b1000 '
b1000 *
1$
#438
0$
#439
b1001 #
b1001 '
b1001 *
1$
#440
0$
#441
b0 #
b0 '
b0 *
b10 "
b10 (
b10 +
1$
#442
0$
#443
b1 #
b1 '
b1 *
1$
#444
0$
#445
b10 #
b10 '
b10 *
1$
#446
0$
#447
b11 #
b11 '
b11 *
1$
#448
0$
#449
b100 #
b100 '
b100 *
1$
#450
0$
#451
b101 #
b101 '
b101 *
1$
#452
0$
#453
b110 #
b110 '
b110 *
1$
#454
0$
#455
b111 #
b111 '
b111 *
1$
#456
0$
#457
b1000 #
b1000 '
b1000 *
1$
#458
0$
#459
b1001 #
b1001 '
b1001 *
1$
#460
0$
#461
b0 #
b0 '
b0 *
b11 "
b11 (
b11 +
1$
#462
0$
#463
b1 #
b1 '
b1 *
1$
#464
0$
#465
b10 #
b10 '
b10 *
1$
#466
0$
#467
b11 #
b11 '
b11 *
1$
#468
0$
#469
b100 #
b100 '
b100 *
1$
#470
0$
#471
b101 #
b101 '
b101 *
1$
#472
0$
#473
b110 #
b110 '
b110 *
1$
#474
0$
#475
b111 #
b111 '
b111 *
1$
#476
0$
#477
b1000 #
b1000 '
b1000 *
1$
#478
0$
#479
b1001 #
b1001 '
b1001 *
1$
#480
0$
#481
b0 #
b0 '
b0 *
b100 "
b100 (
b100 +
1$
#482
0$
#483
b1 #
b1 '
b1 *
1$
#484
0$
#485
b10 #
b10 '
b10 *
1$
#486
0$
#487
b11 #
b11 '
b11 *
1$
#488
0$
#489
b100 #
b100 '
b100 *
1$
#490
0$
#491
b101 #
b101 '
b101 *
1$
#492
0$
#493
b110 #
b110 '
b110 *
1$
#494
0$
#495
b111 #
b111 '
b111 *
1$
#496
0$
#497
b1000 #
b1000 '
b1000 *
1$
#498
0$
#499
b1001 #
b1001 '
b1001 *
1$
#500
0$
#501
b0 #
b0 '
b0 *
b101 "
b101 (
b101 +
1$
#502
0$
0%
