Hamming_15_11_detect/hamming_decoder.sv
module hamming_decoder (
    input  logic [15:0] codeword_in,
    output logic        sed,
    output logic        ded,
    output logic [15:0] codeword_out
);

  logic [15:0] codeword_corr;
  logic [10:0] d;  // Data
  logic [ 4:0] p;  // Parity bits
  logic [ 4:0] check;  // Data bits used for parity calcs
  logic [ 4:0] s;  // Syndrome
  logic [ 4:0] sed_location;  // Syndrome
  logic        s_nonzero;  // Neccesary to get around iVerilog quirk

  // NOTE: Bits being packed from MSB - LSB (like encoder)
  assign d = {
    codeword_in[15],  // d10 → d[10]
    codeword_in[14],  // d9
    codeword_in[13],  // d8
    codeword_in[12],  // d7
    codeword_in[11],  // d6
    codeword_in[10],  // d5
    codeword_in[9],  // d4
    codeword_in[7],  // d3
    codeword_in[6],  // d2
    codeword_in[5],  // d1
    codeword_in[3]  // d0 → d[0]
  };

  assign p = {codeword_in[8], codeword_in[4], codeword_in[2], codeword_in[1], codeword_in[0]};

  // ---------- Computing Syndrome bits
  // repeating parity check from encoder
  assign check[0] = ^codeword_in[15:1];
  assign check[1] = d[0] ^ d[1] ^ d[3] ^ d[4] ^ d[6] ^ d[8] ^ d[10];
  assign check[2] = d[0] ^ d[2] ^ d[3] ^ d[5] ^ d[6] ^ d[9] ^ d[10];
  assign check[3] = d[1] ^ d[2] ^ d[3] ^ d[7] ^ d[8] ^ d[9] ^ d[10];
  assign check[4] = d[4] ^ d[5] ^ d[6] ^ d[7] ^ d[8] ^ d[9] ^ d[10];

  // Calculate syndrome by comparing received parity bits with check
  assign s[0] = p[0] ^ check[0];
  assign s[1] = p[1] ^ check[1];
  assign s[2] = p[2] ^ check[2];
  assign s[3] = p[3] ^ check[3];
  assign s[4] = p[4] ^ check[4];

  assign s_nonzero = |s[4:1];
  assign sed = s_nonzero & s[0];
  assign ded = s_nonzero & ~s[0];
  assign sed_location = {s[4], s[3], s[2], s[1]};

  // Correcting single error detection
  always_comb begin : sec
    codeword_corr = codeword_in;
    if (sed && sed_location != 0) begin
      codeword_corr[sed_location] = ~codeword_in[sed_location];
    end
  end

  // output correct codeword
  assign codeword_out = codeword_corr;
endmodule

Hamming_15_11_detect/hamming_encoder.sv
// NOTE: In Big-Endian data_out
// => 15  14  13  12  11 10 9  8  7  6  5  4  3  2  1  0
// => d10 d9  d8  d7  d6 d5 d4 p4 d3 d2 d1 p3 d0 p2 p1 p0 -> p0 = whole block parity
module hamming_encoder (
    input  logic [10:0] data_in,
    output logic [15:0] data_out
);

  // internal registers
  logic [ 4:0] p_bits;  // 5 parity bits
  logic [15:0] data_concat;

  // // Assign parity bits
  // always_comb begin : assign_parity_bits
  // p_bits[1] = data_in[0] ^ data_in[1] ^ data_in[3] ^ data_in[4] ^ data_in[6] ^ data_in[8] ^ data_in[10];
  // p_bits[2] = data_in[0] ^ data_in[2] ^ data_in[3] ^ data_in[5] ^ data_in[6] ^ data_in[9] ^ data_in[10];
  // p_bits[3] = data_in[1] ^ data_in[2] ^ data_in[3] ^ data_in[7] ^ data_in[8] ^ data_in[9] ^ data_in[10];
  // p_bits[4] = data_in[4] ^ data_in[5] ^ data_in[6] ^ data_in[7] ^ data_in[8] ^ data_in[9] ^ data_in[10];
  // p_bits[0] = ^{data_in,  p_bits[4:1]};  // Overall parity
  // end

  // NOTE: This is for iVerilog constant selects limitations
  // Assign parity separately using continuous assignment
  assign p_bits[1] = data_in[0] ^ data_in[1] ^ data_in[3] ^ data_in[4] ^ data_in[6] ^ data_in[8] ^ data_in[10];
  assign p_bits[2] = data_in[0] ^ data_in[2] ^ data_in[3] ^ data_in[5] ^ data_in[6] ^ data_in[9] ^ data_in[10];
  assign p_bits[3] = data_in[1] ^ data_in[2] ^ data_in[3] ^ data_in[7] ^ data_in[8] ^ data_in[9] ^ data_in[10];
  assign p_bits[4] = data_in[4] ^ data_in[5] ^ data_in[6] ^ data_in[7] ^ data_in[8] ^ data_in[9] ^ data_in[10];
  assign p_bits[0] = ^{data_in, p_bits[4], p_bits[3], p_bits[2], p_bits[1]};

  // concat data and parity
  assign data_out = {data_in[10:4], p_bits[4], data_in[3:1], p_bits[3], data_in[0], p_bits[2:0]};
endmodule

Hamming_15_11_detect/hamming_tb.sv
module hamming_tb;
  logic [10:0] d_in;
  logic [15:0] enc_word;
  logic [15:0] corr_word;
  logic [15:0] dec_word;
  logic [15:0] codeword_in_tb;
  logic        sed;
  logic        ded;

  // instantiate encoder
  hamming_encoder encoder (
      .data_in (d_in),
      .data_out(enc_word)
  );

  // instantiate decoder
  hamming_decoder decoder (
      .codeword_in(codeword_in_tb),
      .codeword_out(dec_word),
      .sed(sed),
      .ded(ded)
  );

  initial begin
    $dumpfile("hamming_tb.vcd");
    $dumpvars(0, hamming_tb);
  end

  task run_no_error_test(input [10:0] din);
    d_in = din;
    #1;

    codeword_in_tb = enc_word;  // no error injected
    #1;

    $display("Original data      = %b", d_in);
    $display("Encoded codeword   = %b", enc_word);
    $display("Decoder input      = %b", codeword_in_tb);
    $display("Decoder output     = %b", dec_word);
    $display("SED: %b, DED: %b", sed, ded);

    if (!sed && !ded && dec_word == enc_word) $display("✅ No-error test passed.\n");
    else $display("❌ No-error test failed.\n");
  endtask

  // Procedure for single-bit error test
  task run_single_error_test(input [10:0] din, input int err_bit);
    d_in = din;
    #1;  // allow encoder to update

    $display("Original data      = %b", d_in);
    $display("Encoded codeword   = %b", enc_word);

    // Inject 1-bit error
    codeword_in_tb = enc_word ^ (16'b1 << err_bit);
    #1;

    $display("Corrupted codeword = %b", decoder.codeword_in);
    $display("Corrected codeword = %b", dec_word);
    $display("SED: %b, DED: %b", sed, ded);

    if (sed && !ded && dec_word == enc_word)
      $display("✅ Single-bit error correctly detected and corrected.\n");
    else $display("❌ Single-bit error test failed.\n");
  endtask

  // Procedure for double-bit error test
  task run_double_error_test(input [10:0] din, input int err_bit1, input int err_bit2);
    d_in = din;
    #1;

    // Inject 2-bit error
    codeword_in_tb = enc_word ^ ((16'b1 << err_bit1) | (16'b1 << err_bit2));
    #1;

    $display("Original data      = %b", d_in);
    $display("Encoded codeword   = %b", enc_word);
    $display("Corrupted codeword = %b", decoder.codeword_in);
    $display("Corrected codeword = %b", dec_word);
    $display("SED: %b, DED: %b", sed, ded);

    if (!sed && ded) $display("✅ Double-bit error correctly detected (not corrected).\n");
    else $display("❌ Double-bit error test failed.\n");
  endtask

  // Main test logic
  initial begin
    $display("Starting Hamming Encoder/Decoder Testbench...\n");
    run_no_error_test(11'b11100011100);  // No error test
    run_single_error_test(11'b10100100100, 5);  // Flip bit 5
    run_single_error_test(11'b00110001110, 13);  // Flip bit 13
    run_double_error_test(11'b10100100100, 5, 10);  // Flip two bits

    $display("All tests complete.");
    $finish;
  end

  // initial begin
  //   // Test vector 1: No error
  //   d_in = 11'b00110001110;
  //   corr_word = enc_word;  // no error injected
  //   #10;
  //
  //   $display("No error test:");
  //   if (sed || ded) $display("FAIL: Detected error when none injected");
  //   else $display("PASS: No error detected as expected");
  //
  //   // Test vector 2: Inject single-bit error
  //   corr_word = enc_word ^ 16'h0004;  // Flip bit 2 for example
  //   #10;
  //
  //   $display("Single-bit error test:");
  //   if (sed && !ded) $display("PASS: Single-bit error detected");
  //   else $display("FAIL: Incorrect error detection");
  //
  //   // check correction:
  //   if (dec_word !== enc_word) $display("PASS: Codeword corrected");
  //   else $display("FAIL: No correction applied");
  //
  //   // Test vector 3: Inject double-bit error
  //   corr_word = enc_word ^ 16'h0004 ^ 16'h0008;  // Flip two bits
  //   #10;
  //
  //   $display("Double-bit error test:");
  //   if (ded) $display("PASS: Double-bit error detected");
  //   else $display("FAIL: Double-bit error not detected");
  //
  //   $finish;
  // end

endmodule

Hamming_15_11_detect/hamming_tb.vcd
$date
	Wed Jun 25 17:11:33 2025
$end
$version
	Icarus Verilog
$end
$timescale
	1s
$end
$scope module hamming_tb $end
$var wire 1 ! sed $end
$var wire 16 " enc_word [15:0] $end
$var wire 1 # ded $end
$var wire 16 $ dec_word [15:0] $end
$var reg 16 % codeword_in_tb [15:0] $end
$var reg 11 & d_in [10:0] $end
$scope module decoder $end
$var wire 16 ' codeword_in [15:0] $end
$var wire 16 ( codeword_out [15:0] $end
$var wire 1 # ded $end
$var wire 1 ! sed $end
$var wire 5 ) sed_location [4:0] $end
$var wire 1 * s_nonzero $end
$var wire 5 + s [4:0] $end
$var wire 5 , p [4:0] $end
$var wire 11 - d [10:0] $end
$var wire 5 . check [4:0] $end
$var reg 16 / codeword_corr [15:0] $end
$scope begin sec $end
$upscope $end
$upscope $end
$scope module encoder $end
$var wire 11 0 data_in [10:0] $end
$var wire 5 1 p_bits [4:0] $end
$var wire 16 2 data_out [15:0] $end
$upscope $end
$scope task run_double_error_test $end
$var reg 11 3 din [10:0] $end
$var integer 32 4 err_bit1 [31:0] $end
$var integer 32 5 err_bit2 [31:0] $end
$upscope $end
$scope task run_no_error_test $end
$var reg 11 6 din [10:0] $end
$upscope $end
$scope task run_single_error_test $end
$var reg 11 7 din [10:0] $end
$var integer 32 8 err_bit [31:0] $end
$upscope $end
$upscope $end
$enddefinitions $end
$comment Show the parameter values. $end
$dumpall
$end
#0
$dumpvars
b0 8
bx 7
b11100011100 6
b0 5
b0 4
bx 3
b1110001011010001 2
b1001 1
b11100011100 0
bx /
bx .
bx -
bx ,
bx +
x*
b0xxxx )
bx (
bx '
b11100011100 &
bx %
bx $
x#
b1110001011010001 "
x!
$end
#1
0#
0*
b0 )
0!
b0 +
b1110001011010001 $
b1110001011010001 (
b1110001011010001 /
b11100011100 -
b1001 ,
b1001 .
b1110001011010001 %
b1110001011010001 '
#2
b11101 1
b1010010101010101 "
b1010010101010101 2
b10100100100 &
b10100100100 0
b101 8
b10100100100 7
#3
1!
1*
b101 )
b1011 +
b1010010101010101 $
b1010010101010101 (
b1010010101010101 /
b10100100110 -
b11101 ,
b10110 .
b1010010101110101 %
b1010010101110101 '
#4
b11000011110011 "
b11000011110011 2
b1011 1
b110001110 &
b110001110 0
b1101 8
b110001110 7
#5
1!
1*
b1101 )
b10000 .
b11011 +
b11000011110011 $
b11000011110011 (
b11000011110011 /
b10001110 -
b1011 ,
b1000011110011 %
b1000011110011 '
#6
b1010010101010101 "
b1010010101010101 2
b11101 1
b10100100100 &
b10100100100 0
b1010 5
b101 4
b10100100100 3
#7
1#
0!
b1111 )
b11110 +
b1010000101110101 $
b1010000101110101 (
b1010000101110101 /
b10100000110 -
b11101 ,
b11 .
b1010000101110101 %
b1010000101110101 '
