Vending_FSM/vending_fsm.sv
// NOTE:  The token price of a beverage is 5 cents,
// and our specially designed beverage vending machine
// only  accepts tokens of 1 cent, 2 cents and 5 cents.
// The task of the laboratory is to design a finite state machine
// for the automatic beverage vending machine. The following table
// shows the interface signals required for  this design.

// NOTE: Port Names | Port Direction | Port Size
//       -----------|----------------|----------
//          clk     | input          | 1 bit
//          reset   | input          | 1 bit
//          one     | input          | 1 bit
//          two     | input          | 1 bit
//          five    | input          | 1 bit
//          d       | output         | 1 bit
//          r       | output         | 3 bits

module vending_fsm (
    input  logic       clk,
    input  logic       reset,
    input  logic       one,
    input  logic       two,
    input  logic       five,
    output logic       d,
    output logic [2:0] r
);

  localparam logic S0 = 3'b000;
  localparam logic S1 = 3'b001;
  localparam logic S2 = 3'b010;
  localparam logic S3 = 3'b011;
  localparam logic S4 = 3'b100;
  localparam logic S5 = 3'b101;

  logic [2:0] state, next_state;
  logic [2:0] next_r;
  always_ff @(posedge clk or posedge reset) begin : state_transition
    if (reset) begin
      state <= S0;
    end else begin
      state <= next_state;
    end
  end

  always_comb begin : state_logic
    case (state)
      S0: begin
        if (one) begin
          next_state = S1;
        end else if (two) begin
          next_state = S2;
        end else if (five) begin
          next_state = S5;
        end else begin
          next_state = S0;
        end
      end
      S1: begin
        if (one) begin
          next_state = S2;
        end else if (two) begin
          next_state = S3;
        end else if (five) begin
          next_state = S5;
        end else begin
          next_state = S1;
        end

      end
      S2: begin
        if (one) begin
          next_state = S3;
        end else if (two) begin
          next_state = S4;
        end else if (five) begin
          next_state = S5;
        end else begin
          next_state = S2;
        end

      end
      S3: begin
        if (one) begin
          next_state = S4;
        end else if (two) begin
          next_state = S5;
        end else if (five) begin
          next_state = S5;
        end else begin
          next_state = S3;
        end

      end
      S4: begin
        if (one) begin
          next_state = S5;
        end else if (two) begin
          next_state = S5;
        end else if (five) begin
          next_state = S5;
        end else begin
          next_state = S4;
        end

      end
      S5: begin
        if (one) begin
          next_state = S1;
        end else if (two) begin
          next_state = S2;
        end else if (five) begin
          next_state = S5;
        end else begin
          next_state = S0;
        end
      end
      default: next_state = S0;
    endcase
  end

  always_comb begin : remainder_logic
    case (state)
      S0: r = 0;
      S1: r = five ? 1 : 0;
      S2: r = five ? 2 : 0;
      S3: r = five ? 3 : 0;
      S4: r = two ? 1 : five ? 4 : 0;
      S5: r = 0;
      default: r = 0;
    endcase
  end
  // FIXME: d being held high outside of state S5
  assign d = (state == S5);
endmodule

Vending_FSM/vending_fsm_tb.sv
module vending_fsm_tb;

  logic clk, reset;
  logic one, two, five;
  logic d;
  logic [2:0] r;

  // Instantiate the DUT
  vending_fsm dut (
      .clk(clk),
      .reset(reset),
      .one(one),
      .two(two),
      .five(five),
      .d(d),
      .r(r)
  );

  // Clock generation: 10ns period
  initial clk = 0;
  always #5 clk = ~clk;

  // Stimulus
  initial begin
    $dumpfile("vending_fsm.vcd");
    $dumpvars(0, vending_fsm_tb);

    // Initialize inputs
    reset = 1;
    one   = 0;
    two   = 0;
    five  = 0;
    #12;
    reset = 0;

    // Insert 1 + 2 + 2 = 5 cents → should dispense
    insert_token(1'b1, 1'b0, 1'b0);  // 1 cent
    insert_token(1'b0, 1'b1, 1'b0);  // 2 cent
    insert_token(1'b0, 1'b1, 1'b0);  // 2 cent

    // // Insert 5 directly → should dispense
    // insert_token(1'b0, 1'b0, 1'b1);  // 5 cent
    //
    // // Insert 2 + 2 = 4, then 2 → overpay → r = 1
    // insert_token(1'b0, 1'b1, 1'b0);  // 2 cent
    // insert_token(1'b0, 1'b1, 1'b0);  // 2 cent
    // insert_token(1'b0, 1'b1, 1'b0);  // 2 cent

    // Idle for a few cycles
    #50;
    $finish;
  end

  // Task to insert a token
  task insert_token(input logic one_in, two_in, five_in);
    begin
      @(negedge clk);
      one  = one_in;
      two  = two_in;
      five = five_in;
      @(negedge clk);
      one  = 0;
      two  = 0;
      five = 0;
    end
  endtask

endmodule

Vending_FSM/vending_fsm.vcd
$date
	Tue Jun 10 01:31:40 2025
$end
$version
	Icarus Verilog
$end
$timescale
	1s
$end
$scope module vending_fsm_tb $end
$var wire 3 ! r [2:0] $end
$var wire 1 " d $end
$var reg 1 # clk $end
$var reg 1 $ five $end
$var reg 1 % one $end
$var reg 1 & reset $end
$var reg 1 ' two $end
$scope module dut $end
$var wire 1 # clk $end
$var wire 1 $ five $end
$var wire 1 % one $end
$var wire 1 & reset $end
$var wire 1 ' two $end
$var wire 1 " d $end
$var parameter 1 ( S0 $end
$var parameter 1 ) S1 $end
$var parameter 1 * S2 $end
$var parameter 1 + S3 $end
$var parameter 1 , S4 $end
$var parameter 1 - S5 $end
$var reg 3 . next_state [2:0] $end
$var reg 3 / r [2:0] $end
$var reg 3 0 state [2:0] $end
$scope begin remainder_logic $end
$upscope $end
$scope begin state_logic $end
$upscope $end
$scope begin state_transition $end
$upscope $end
$upscope $end
$scope task insert_token $end
$var reg 1 1 five_in $end
$var reg 1 2 one_in $end
$var reg 1 3 two_in $end
$upscope $end
$upscope $end
$enddefinitions $end
$comment Show the parameter values. $end
$dumpall
1-
0,
1+
0*
1)
0(
$end
#0
$dumpvars
x3
x2
x1
b0 0
b0 /
b0 .
0'
1&
0%
0$
0#
0"
b0 !
$end
#5
1#
#10
0#
#12
01
03
12
0&
#15
1#
#20
b1 .
1%
0#
#25
b0 .
1"
b1 0
1#
#30
b1 .
13
02
0%
0#
#35
1#
#40
1'
0#
#45
1#
#50
0'
0#
#55
1#
#60
1'
0#
#65
1#
#70
0'
0#
